{
  "1": [
    "索爱",
    "SA",
    "MP3",
    "白领丽人",
    "插式"
  ],
  "2": [
    "WB1000",
    "机器",
    "三星",
    "不错",
    "十几"
  ],
  "3": [
    "经济",
    "预期",
    "估值",
    "华安",
    "复苏"
  ],
  "4": [
    "伊凡",
    "索菲",
    "安娜",
    "柜子",
    "铜币"
  ],
  "5": [
    "奥尼尔",
    "邓肯",
    "谢幕",
    "甩卖",
    "鲨鱼"
  ],
  "6": [
    "湖人队",
    "韦斯特",
    "吃惊",
    "教练",
    "小牛队"
  ],
  "7": [
    "季报",
    "上市公司",
    "重仓股",
    "业绩",
    "披露"
  ],
  "8": [
    "量子",
    "危机",
    "一刀",
    "皇家",
    "赌场"
  ],
  "9": [
    "宾得",
    "x",
    "K",
    "机器",
    "入门"
  ],
  "10": [
    "宝贝",
    "攻城",
    "怪物",
    "装备",
    "刷装备"
  ],
  "11": [
    "金币",
    "游戏币",
    "交易",
    "收购",
    "买金"
  ],
  "12": [
    "时空",
    "劳模",
    "证书",
    "兑换",
    "紫装"
  ],
  "13": [
    "ETF",
    "指数",
    "申购",
    "产品",
    "亿份"
  ],
  "14": [
    "华商",
    "盛世",
    "基金",
    "晨星",
    "型基金"
  ],
  "15": [
    "结拜",
    "豪侠",
    "忠义堂",
    "受热捧",
    "梁山泊"
  ],
  "16": [
    "体育",
    "詹姆斯",
    "停摆",
    "挑毛病",
    "打球"
  ],
  "17": [
    "银河",
    "评级",
    "基金",
    "国金",
    "投研"
  ],
  "18": [
    "奥尼尔",
    "鲨鱼",
    "出战",
    "詹姆斯",
    "韦德"
  ],
  "19": [
    "GF1",
    "松下",
    "编码",
    ".264",
    "H"
  ],
  "20": [
    "HS20",
    "松下",
    "全高清",
    "MOS",
    "状态"
  ],
  "21": [
    "阿凡达",
    "正版",
    "文化部",
    "手机游戏",
    "电影"
  ],
  "22": [
    "亚洲",
    "易建联",
    "雷霆",
    "身高",
    "阿联"
  ],
  "23": [
    "基金",
    "百分点",
    "加仓",
    "股票",
    "仓位"
  ],
  "24": [
    "ZS3",
    "松下",
    "液晶显示",
    "长焦端",
    "初学者"
  ],
  "25": [
    "博时基金",
    "高端",
    "论坛",
    "客户",
    "举办"
  ],
  "26": [
    "GLITTER",
    "耳塞",
    "面板",
    "GREEN",
    "HOUSE"
  ],
  "27": [
    "迪士尼",
    "青蛙",
    "动画",
    "设计图",
    "公主"
  ],
  "28": [
    "宾得",
    "K",
    "x",
    "DA",
    "F4AL"
  ],
  "29": [
    "浩克",
    "无敌",
    "绿巨人",
    "票房",
    "木乃伊"
  ],
  "30": [
    "货币",
    "何俊春",
    "缩短",
    "基金",
    "市场"
  ],
  "31": [
    "波什",
    "脖子",
    "龙王",
    "提问",
    "症状"
  ],
  "32": [
    "分红",
    "月份",
    "基金",
    "型基金",
    "偏股"
  ],
  "33": [
    "Mark",
    "II",
    "灰尘",
    "对焦",
    "D"
  ],
  "34": [
    "宝石",
    "原石",
    "属性",
    "合成",
    "暴击"
  ],
  "35": [
    "湖人",
    "防守",
    "禅师",
    "小牛",
    "篮下"
  ],
  "36": [
    "国债",
    "品种",
    "债券",
    "收益率",
    "债市"
  ],
  "37": [
    "亿美元",
    "对冲",
    "顶尖",
    "赚取",
    "基金"
  ],
  "38": [
    "转接",
    "鱼眼",
    "GIZMON",
    "专用",
    "MICRO"
  ],
  "39": [
    "ETGAME",
    "恒信",
    "仙剑",
    "古典",
    "建筑"
  ],
  "40": [
    "T900",
    "索尼",
    "卡片机",
    "home",
    "16.3"
  ],
  "41": [
    "麦基",
    "扣篮",
    "贾维",
    "吉尼斯",
    "起跳"
  ],
  "42": [
    "火箭",
    "贾斯",
    "候选人",
    "人选",
    "亚历山大"
  ],
  "43": [
    "并购",
    "集团",
    "华夏",
    "基金",
    "万股"
  ],
  "44": [
    "小青",
    "女儿国",
    "呵呵",
    "女生",
    "难忘"
  ],
  "45": [
    "P3",
    "YP",
    "三星",
    "小时",
    "DNSe3"
  ],
  "46": [
    "赤壁",
    "OL",
    "诸侯",
    "g2us",
    "大战"
  ],
  "47": [
    "文明",
    "II",
    "升级",
    "玩家",
    "赚钱"
  ],
  "48": [
    "雷霆",
    "杜兰特",
    "得手",
    "领先",
    "梅奥"
  ],
  "49": [
    "战胜",
    "做到",
    "太阳",
    "雷霆",
    "韦德"
  ],
  "50": [
    "员工",
    "万份",
    "份额",
    "基金",
    "占该"
  ],
  "51": [
    "詹姆斯",
    "韦德",
    "詹韦",
    "篮板",
    "绿衫"
  ],
  "52": [
    "卢浮宫",
    "明亮",
    "法国",
    "女主角",
    "女神"
  ],
  "53": [
    "七龙珠",
    "龙珠迷",
    "悟空",
    "龙珠",
    "票房"
  ],
  "54": [
    "X",
    "战警",
    "金刚",
    "剧照",
    "海报"
  ],
  "55": [
    "渴望",
    "意志",
    "斯帅",
    "完美",
    "波尔"
  ],
  "56": [
    "索尼",
    "取景",
    "初学者",
    "选项",
    "显示屏"
  ],
  "57": [
    "副官",
    "宝箱",
    "劳动节",
    "成长",
    "海贼王"
  ],
  "58": [
    "分红",
    "张远忠",
    "条款",
    "利润",
    "约定"
  ],
  "59": [
    "J35",
    "富士",
    "全景",
    "场景",
    "像素"
  ],
  "60": [
    "范甘迪",
    "湖人队",
    "杰克逊",
    "马克",
    "紧迫感"
  ],
  "61": [
    "腾龙",
    "XR",
    "VC",
    ".8",
    "F2"
  ],
  "62": [
    "基金",
    "加权",
    "收益率",
    "指数",
    "平均"
  ],
  "63": [
    "基金",
    "长城",
    "景顺",
    "份额",
    "赎回"
  ],
  "64": [
    "克鲁斯",
    "汤姆",
    "串串",
    "大风大浪",
    "军官"
  ],
  "65": [
    "H106",
    "固态",
    "硬盘",
    "三星",
    "DV"
  ],
  "66": [
    "华宝",
    "证券",
    "代销",
    "资格",
    "基金"
  ],
  "67": [
    "佳能",
    "卡口",
    "D",
    "EF",
    "镜头"
  ],
  "68": [
    "经济",
    "新能源",
    "节能",
    "行业",
    "方向"
  ],
  "69": [
    "舞台",
    "探长",
    "戈登",
    "戏剧",
    "演员"
  ],
  "70": [
    "资产",
    "诺安",
    "基金",
    "投资",
    "债券"
  ],
  "71": [
    "神契",
    "online",
    "内测",
    "客户端",
    "游戏"
  ],
  "72": [
    "T90",
    "索尼",
    "带票",
    "T77",
    "数码相机"
  ],
  "73": [
    "斯莱特",
    "感谢",
    "影后",
    "读者",
    "曝用"
  ],
  "74": [
    "巴蒂尔",
    "马刺",
    "鲍文",
    "篮板",
    "布鲁斯"
  ],
  "75": [
    "武神",
    "拉阔",
    "动作游戏",
    "新鲜出炉",
    "传说"
  ],
  "76": [
    "安吉",
    "失望",
    "热火",
    "疲劳",
    "淘汰"
  ],
  "77": [
    "佣金",
    "分仓",
    "券商",
    "基金",
    "亿元"
  ],
  "78": [
    "G11",
    "转盘",
    "操作性",
    "佳能",
    "光学"
  ],
  "79": [
    "Fi",
    "环绕",
    "保真",
    "降噪",
    "耳机"
  ],
  "80": [
    "马布里",
    "礼物",
    "奶油",
    "午餐",
    "沈阳"
  ],
  "81": [
    "公牛",
    "老鹰",
    "回合",
    "两队",
    "阵容"
  ],
  "82": [
    "封神",
    "双倍",
    "ol",
    "激情",
    "经验"
  ],
  "83": [
    "极品",
    "小凤姐",
    "痘痘",
    "眼镜",
    "三百年"
  ],
  "84": [
    "法国",
    "法国电影",
    "影坛",
    "新闻节目",
    "皮草"
  ],
  "85": [
    "奥尼尔",
    "复出",
    "两队",
    "回合",
    "鲨鱼"
  ],
  "86": [
    "男篮",
    "江苏",
    "黄金",
    "唐正东",
    "广东"
  ],
  "87": [
    "HF20",
    "闪存",
    "佳能",
    "全高清",
    "i"
  ],
  "88": [
    "C140",
    "柯达",
    "机型",
    "消费者",
    "情景模式"
  ],
  "89": [
    "T11TE",
    "蓝魔",
    "OTG",
    "输出",
    "整合"
  ],
  "90": [
    "WX1",
    "索尼",
    "Exmor",
    "R",
    "传感器"
  ],
  "91": [
    "老鹰",
    "公牛",
    "罗斯",
    "炮灰",
    "IV"
  ],
  "92": [
    "博伊尔",
    "印度",
    "贾麦尔",
    "丹尼",
    "百万富翁"
  ],
  "93": [
    "T900",
    "索尼",
    "一代",
    "3.5",
    "像素"
  ],
  "94": [
    "ES60",
    "三星",
    "拍摄",
    ".2",
    "支持"
  ],
  "95": [
    "FP8",
    "松下",
    "4.6",
    "光学",
    "放奔"
  ],
  "96": [
    "疑云",
    "瓦力",
    "机器人",
    "富翁",
    "贫民"
  ],
  "97": [
    "挂机",
    "封神",
    "免费",
    "决战",
    "挂出"
  ],
  "98": [
    "HOTT",
    "HD360",
    "容量",
    "高清",
    "解码"
  ],
  "99": [
    "SX200",
    "cm",
    "佳能",
    "广角",
    "变焦"
  ],
  "100": [
    "ST50",
    "智能",
    "三星",
    "拍摄",
    "美容"
  ],
  "101": [
    "榜单",
    "亿美元",
    "赚钱",
    "投资人",
    "保尔森"
  ],
  "102": [
    "IXUS",
    "IS",
    "佳能",
    "检测",
    "色彩"
  ],
  "103": [
    "木马",
    "话费",
    "拨打",
    "Sophos",
    "Anti"
  ],
  "104": [
    "雷霆",
    "进攻",
    "篮板",
    "对阵",
    "比赛"
  ],
  "105": [
    "D90",
    "尼康",
    "短片",
    "降到",
    "单机"
  ],
  "106": [
    "W190",
    "索尼",
    "家用",
    "合格",
    "x240"
  ],
  "107": [
    "C140",
    "柯达",
    "卡片机",
    "家用",
    "千万级"
  ],
  "108": [
    "礼包",
    "变形",
    "合区",
    "阶骑",
    "BOSS"
  ],
  "109": [
    "林肯",
    "小布什",
    "曼德拉",
    "总统",
    "W"
  ],
  "110": [
    "加尔松",
    "纪录片",
    "达尔文",
    "噩梦",
    "巴黎"
  ],
  "111": [
    "至尊",
    "昆仑",
    "移动",
    "手机游戏",
    "中国"
  ],
  "112": [
    "分红",
    "基金",
    "国海",
    "富兰克林",
    "份额"
  ],
  "113": [
    "小锤",
    "启示录",
    "障碍物",
    "妙用",
    "试玩版"
  ],
  "114": [
    "梅奥",
    "外线",
    "第一节",
    "下半场",
    "霍林斯"
  ],
  "115": [
    "看着",
    "哈队",
    "更衣室",
    "波士顿",
    "坐在"
  ],
  "116": [
    "武器",
    "强化",
    "攻击力",
    "部位",
    "剑柄"
  ],
  "117": [
    "查维斯",
    "斯通",
    "纪录片",
    "奥立佛",
    "委内瑞拉"
  ],
  "118": [
    "克罗斯",
    "斯莱特",
    "情爱",
    "戴维",
    "朗读"
  ],
  "119": [
    "汤圆",
    "天域",
    "山楂",
    "杏仁",
    "朱古力"
  ],
  "120": [
    "疑云",
    "男配角",
    "提名",
    "The",
    "女配角"
  ],
  "121": [
    "赤壁",
    "女性",
    "OL",
    "幸福",
    "g2us"
  ],
  "122": [
    "活宝",
    "喜剧",
    "西恩",
    "凯瑞",
    "出演"
  ],
  "123": [
    "分红",
    "折价率",
    "封闭式",
    "封基",
    "基金"
  ],
  "124": [
    "意大利",
    "阿富汗",
    "影展",
    "罗马",
    "决议案"
  ],
  "125": [
    "下跌",
    "基指",
    "ETF",
    "基金",
    "跌幅"
  ],
  "126": [
    "蜀山",
    "战斗",
    "RPG",
    "仙侠",
    "格斗游戏"
  ],
  "127": [
    "大腿",
    "搞怪",
    "现场",
    "嘉宾",
    "海瑟薇"
  ],
  "128": [
    "基金",
    "业绩",
    "收益率",
    "踏错",
    "成立"
  ],
  "129": [
    "阳阳",
    "郑有杰",
    "小茹",
    "李安",
    "李岗"
  ],
  "130": [
    "皮帕",
    "私人生活",
    "身穿",
    "基努",
    "现身"
  ],
  "131": [
    "优惠",
    "游戏",
    "手机用户",
    "玩家",
    "多多"
  ],
  "132": [
    "阿泰",
    "禁赛",
    "巴里",
    "冷漠",
    "往前走"
  ],
  "133": [
    "灵兽",
    "参战",
    "奖励",
    "祭奠",
    "经验"
  ],
  "134": [
    "J250",
    "富士",
    "光学",
    "变焦",
    "小巧"
  ],
  "135": [
    "三国",
    "灯谜",
    "明珠",
    "掌上明珠",
    "农历"
  ],
  "136": [
    "x",
    "K",
    "用户",
    "宾得",
    "带给"
  ],
  "137": [
    "募集",
    "基金",
    "荷银",
    "品质",
    "邵泽慧"
  ],
  "138": [
    "终结者",
    "T",
    "曝光",
    "Terminator",
    "Salvation"
  ],
  "139": [
    "普林斯",
    "活塞",
    "卡莱尔",
    "防守",
    "麦蒂"
  ],
  "140": [
    "MOTO",
    "诺基亚",
    "索爱",
    "天行",
    "英汉"
  ],
  "141": [
    "经验",
    "封神",
    "ol",
    "挂机",
    "混元"
  ],
  "142": [
    "上涨",
    "ETF",
    "开盘",
    "全线",
    "午盘"
  ],
  "143": [
    "华商",
    "型基金",
    "收益率",
    "大盘",
    "基金"
  ],
  "144": [
    "转生",
    "寄卖",
    "金币",
    "乱世",
    "玩家"
  ],
  "145": [
    "花店",
    "AFM",
    "出口",
    "赵仁成",
    "韩国"
  ],
  "146": [
    "神秘",
    "棒棒",
    "小棒",
    "传情",
    "达意"
  ],
  "147": [
    "不错",
    "疯子",
    "湖人",
    "坚信",
    "笑容"
  ],
  "148": [
    "杰昆",
    "Phoenix",
    "音乐",
    "首映式",
    "退出"
  ],
  "149": [
    "ASPH",
    "GF1",
    "LUMIX",
    "抵达",
    "西安"
  ],
  "150": [
    "EOS",
    "D",
    "佳能",
    "电视机",
    "万点"
  ],
  "151": [
    "每题",
    "活动",
    "答对",
    "喇叭",
    "棒棒"
  ],
  "152": [
    "李安",
    "大杂烩",
    "伍德斯",
    "参半",
    "好坏"
  ],
  "153": [
    "朱莉",
    "产后",
    "新民",
    "贝克曼",
    "贝托夫"
  ],
  "154": [
    "马丁",
    "李安",
    "伍德斯",
    "片花",
    "曝光"
  ],
  "155": [
    "伤害",
    "技能",
    "隔山",
    "魔族",
    "施放"
  ],
  "156": [
    "小牛",
    "替补",
    "湖人",
    "包夹",
    "佩贾"
  ],
  "157": [
    "友邦",
    "增利",
    "华泰",
    "稳本",
    "第八次"
  ],
  "158": [
    "富翁",
    "贫民",
    "录音师",
    "CAS",
    "Quantum"
  ],
  "159": [
    "首饰",
    "宝箱",
    "开出",
    "技能",
    "神秘"
  ],
  "160": [
    "家伙",
    "韩国",
    "电视剧",
    "约合",
    "韩片"
  ],
  "161": [
    "灵兽",
    "装备",
    "合成",
    "材料",
    "星级"
  ],
  "162": [
    "灰尘",
    "除尘",
    "图像",
    "感应器",
    "EOS"
  ],
  "163": [
    "佳能",
    "D",
    "防抖",
    "调整",
    "降百元"
  ],
  "164": [
    "替身",
    "哈利",
    "特技",
    "波特",
    "受伤"
  ],
  "165": [
    "A500",
    "索尼",
    "续航",
    "DRO",
    "配备"
  ],
  "166": [
    "变形金刚",
    "上映",
    "复仇者",
    "Avenger",
    "公映"
  ],
  "167": [
    "乔尔",
    "热火",
    "隆多",
    "Z",
    "带伤"
  ],
  "168": [
    "南奎丽",
    "考死",
    "短裙",
    "防走光",
    "低胸"
  ],
  "169": [
    "沃尔塔",
    "巴黎",
    "剧组",
    "吕克",
    "贝松"
  ],
  "170": [
    "P2",
    "E",
    "GF1",
    "ZUIKO",
    "DIGITAL"
  ],
  "171": [
    "D3S",
    "感光度",
    "尼康",
    "规格",
    "画幅"
  ],
  "172": [
    "私募",
    "净值",
    "股权",
    "基金",
    "投资"
  ],
  "173": [
    "荣耀",
    "大陆",
    "OL",
    "问世",
    "力量"
  ],
  "174": [
    "星座",
    "LS85",
    "美眉",
    "松下",
    "白羊座"
  ],
  "175": [
    "D3000",
    "对焦",
    "尼康",
    "自动",
    "物体"
  ],
  "176": [
    "经济",
    "内需",
    "投资",
    "行业",
    "消化"
  ],
  "177": [
    "布泽尔",
    "脚伤",
    "韧带",
    "脚趾",
    "公牛"
  ],
  "178": [
    "横扫",
    "湖人",
    "火箭",
    "魔术",
    "子弹"
  ],
  "179": [
    "华商",
    "盛世",
    "基金",
    "收益",
    "周报"
  ],
  "180": [
    "基金",
    "陈良",
    "监管",
    "监督",
    "保值"
  ],
  "181": [
    "章子怡",
    "温婉",
    "孟小冬",
    "骑士",
    "中变"
  ],
  "182": [
    "基金",
    "赎回",
    "申购",
    "亿份",
    "股票"
  ],
  "183": [
    "D90",
    "尼康",
    "像素",
    "短片",
    "D70"
  ],
  "184": [
    "周星驰",
    "青蜂",
    "加藤",
    "扮演",
    "执导"
  ],
  "185": [
    "詹姆斯",
    "吉尔伯",
    "骑士",
    "老板",
    "私事"
  ],
  "186": [
    "折价率",
    "基金",
    "封基",
    "封闭式",
    "十只"
  ],
  "187": [
    "APPSTORE",
    "帐号",
    "坏账",
    "iPhone",
    "WiSTONE"
  ],
  "188": [
    "电影节",
    "克鲁尼",
    "The",
    "塞隆",
    "查理"
  ],
  "189": [
    "FS200",
    "变焦",
    "摄像机",
    "佳能",
    "BP"
  ],
  "190": [
    "天弘",
    "基金",
    "吕宜振",
    "证券",
    "经理"
  ],
  "191": [
    "湖人",
    "基德",
    "小牛",
    "钱德勒",
    "史蒂文森"
  ],
  "192": [
    "加勒比海",
    "生化",
    "戈尔",
    "奇兵",
    "The"
  ],
  "193": [
    "卢克",
    "福德",
    "Michelle",
    "杨紫琼",
    "李连杰"
  ],
  "194": [
    "佳能",
    "D",
    "套机",
    "中端",
    "产品报价"
  ],
  "195": [
    "宝石",
    "强化",
    "一级",
    "排行",
    "侠义"
  ],
  "196": [
    "酿酒",
    "山西汾酒",
    "股东",
    "基金",
    "年报"
  ],
  "197": [
    "神域",
    "封测",
    "玩家",
    "服务器",
    "人山人海"
  ],
  "198": [
    "霸王",
    "II",
    "新区",
    "指游",
    "PK"
  ],
  "199": [
    "控卫",
    "时代",
    "大个子",
    "罗斯",
    "步行者"
  ],
  "200": [
    "宝石",
    "锻造",
    "几率",
    "合成",
    "防御"
  ],
  "201": [
    "年金",
    "路透",
    "计划",
    "汤森",
    "企业"
  ],
  "202": [
    "D5000",
    "尼康",
    "翻转",
    "处理",
    "带有"
  ],
  "203": [
    "诛神",
    "镖车",
    "online",
    "任务",
    "运镖"
  ],
  "204": [
    "广告",
    "转播",
    "电影",
    "播放",
    "禁令"
  ],
  "205": [
    "提名",
    "名单",
    "人民",
    "奖提名",
    "电影"
  ],
  "206": [
    "棒棒",
    "账号",
    "投票",
    "super",
    "首页"
  ],
  "207": [
    "张庆鹏",
    "新疆",
    "王治郅",
    "巴特尔",
    "比赛"
  ],
  "208": [
    "电影",
    "神机",
    "韩国",
    "亿韩元",
    "预算"
  ],
  "209": [
    "詹姆斯",
    "皇帝",
    "三分",
    "查尔",
    "裁判"
  ],
  "210": [
    "私募",
    "基金",
    "公募",
    "业绩",
    "信托"
  ],
  "211": [
    "老鹰",
    "公牛",
    "缴出",
    "内线",
    "三分"
  ],
  "212": [
    "权相宇",
    "李宝英",
    "悲伤",
    "校服",
    "人父"
  ],
  "213": [
    "富翁",
    "贫民",
    "英国",
    "BAFTA",
    "制片厂"
  ],
  "214": [
    "梁华栋",
    "景顺",
    "长城",
    "总经理",
    "辞职"
  ],
  "215": [
    "超广角",
    "松下",
    "LX3GK",
    "1.63",
    "元件"
  ],
  "216": [
    "基金",
    "分红",
    "金红利",
    "分配",
    "汉盛"
  ],
  "217": [
    "火箭队",
    "弗兰克",
    "德韦恩",
    "人选",
    "助教"
  ],
  "218": [
    "喜马拉雅",
    "崔岷植",
    "摆脱",
    "压抑",
    "电影"
  ],
  "219": [
    "GX200",
    "理光",
    "VF",
    "朋友",
    "超广角"
  ],
  "220": [
    "韦德",
    "闪电侠",
    "看球",
    "膝盖",
    "不忍"
  ],
  "221": [
    "基金",
    "华夏",
    "第十八次",
    "分红",
    "份派"
  ],
  "222": [
    "M927",
    "纽曼",
    "GB",
    "播放",
    "支持"
  ],
  "223": [
    "索尼",
    "XR100E",
    "硬盘",
    "影像",
    "摄像机"
  ],
  "224": [
    "银行",
    "追查",
    "柏林",
    "跨国",
    "电影节"
  ],
  "225": [
    "管理费",
    "基金",
    "收入",
    "公司",
    "增速"
  ],
  "226": [
    "S205EXR",
    "Pro",
    "富士",
    "Focus",
    "Low"
  ],
  "227": [
    "E200",
    "艾利和",
    "支持",
    "iriver",
    "录音"
  ],
  "228": [
    "热火",
    "奥尼尔",
    "本场",
    "名单",
    "主帅"
  ],
  "229": [
    "Z200fd",
    "富士",
    "机器",
    "特写",
    "自拍"
  ],
  "230": [
    "WB1000",
    "三星",
    "AMOLED",
    "防滑",
    "防抖"
  ],
  "231": [
    "赤壁",
    "纵横",
    "OL",
    "移动",
    "战车"
  ],
  "232": [
    "奖品",
    "大屏",
    "测试",
    "手机",
    "英雄"
  ],
  "233": [
    "欧元",
    "报酬",
    "剧组",
    "年轻人",
    "吕克"
  ],
  "234": [
    "商城",
    "促销",
    "D",
    "直逼",
    "类产品"
  ],
  "235": [
    "子龙",
    "三国",
    "无双",
    "赵云",
    "直枪"
  ],
  "236": [
    "申购",
    "华宝",
    "兴业",
    "金额",
    "最低"
  ],
  "237": [
    "樟柯",
    "萨拉热窝",
    "柏林",
    "电影节",
    "忙于"
  ],
  "238": [
    "续集",
    "金刚",
    "哈利",
    "波特",
    "前传"
  ],
  "239": [
    "IS",
    "IXUS",
    "佳能",
    "mm",
    "DIGIC"
  ],
  "240": [
    "宝石",
    "神契",
    "法术",
    "属性",
    "抗性"
  ],
  "241": [
    "EOS",
    "D",
    "感应器",
    "对焦",
    "自动"
  ],
  "242": [
    "HF200",
    "佳能",
    "闪存",
    "DV",
    "套装"
  ],
  "243": [
    "天行",
    "乐园",
    "过招",
    "show",
    "自信"
  ],
  "244": [
    "赎回",
    "基金",
    "亿元",
    "亏损",
    "型基金"
  ],
  "245": [
    "钱德勒",
    "禁区",
    "底线",
    "篮筐",
    "站直"
  ],
  "246": [
    "股份",
    "基金",
    "个股",
    "股票",
    "隐形"
  ],
  "247": [
    "游戏城",
    "小奥",
    "灾区",
    "靓号",
    "人民"
  ],
  "248": [
    "A500",
    "索尼",
    "套机",
    "中关村",
    "可折叠"
  ],
  "249": [
    "印度",
    "Jai",
    "富翁",
    "贫民",
    "舞曲"
  ],
  "250": [
    "玩家",
    "神兆",
    "新区",
    "开服",
    "升级"
  ],
  "251": [
    "斯基",
    "波兰",
    "撤销",
    "诱奸",
    "案件"
  ],
  "252": [
    "昂赛",
    "子弹",
    "MVP",
    "天赋",
    "荣誉"
  ],
  "253": [
    "上古",
    "II",
    "封测",
    "清新",
    "Q版"
  ],
  "254": [
    "三国",
    "印魂",
    "长安",
    "任务",
    "地图"
  ],
  "255": [
    "小丑",
    "蝙蝠侠",
    "海报",
    "偷取",
    "莱杰"
  ],
  "256": [
    "加索尔",
    "皮球",
    "湖人",
    "禅师",
    "弹筐"
  ],
  "257": [
    "宝石",
    "极品",
    "合成",
    "人气",
    "源质"
  ],
  "258": [
    "资料片",
    "封神",
    "PK",
    "决战",
    "ol"
  ],
  "259": [
    "韦德",
    "詹姆斯",
    "热火",
    "老将",
    "加内特"
  ],
  "260": [
    "通缉令",
    "朱莉",
    "麦卡沃",
    "贝克曼",
    "贝托夫"
  ],
  "261": [
    "创业板",
    "基金",
    "投资",
    "市场",
    "分流"
  ],
  "262": [
    "朱平",
    "全球化",
    "投资者",
    "中国",
    "全球"
  ],
  "263": [
    "海峰",
    "重组",
    "私募",
    "行业",
    "公募"
  ],
  "264": [
    "古墓",
    "宝藏",
    "遗址",
    "九州",
    "勇士"
  ],
  "265": [
    "杰克逊",
    "脚踝",
    "第五场",
    "借口",
    "愿用"
  ],
  "266": [
    "孙艺珍",
    "携手",
    "小说",
    "出演",
    "同名"
  ],
  "267": [
    "掘金",
    "雷霆",
    "杜兰特",
    "劳森",
    "三分"
  ],
  "268": [
    "韦斯特",
    "皮尔斯",
    "下场",
    "一名",
    "热火"
  ],
  "269": [
    "中国联通",
    "联通",
    "亿元",
    "基金",
    "电信"
  ],
  "270": [
    "支付",
    "哆可",
    "易宝",
    "游戏",
    "成都"
  ],
  "271": [
    "帝国",
    "宠物",
    "资料片",
    "神器",
    "武器"
  ],
  "272": [
    "口袋",
    "传说",
    "iPad",
    "掌握",
    "动物"
  ],
  "273": [
    "D",
    "测光",
    "EOS",
    "佳能",
    "机身"
  ],
  "274": [
    "李振宁",
    "A股",
    "价值",
    "牛市",
    "中国"
  ],
  "275": [
    "葬送",
    "直击",
    "热火",
    "TD",
    "carry"
  ],
  "276": [
    "湖人队",
    "阵容",
    "停摆",
    "进攻",
    "球队"
  ],
  "277": [
    "湖人",
    "落后",
    "小牛",
    "局面",
    "比赛"
  ],
  "278": [
    "D3000",
    "尼康",
    "水准",
    "做工",
    "简化"
  ],
  "279": [
    "D90",
    "短片",
    "像素",
    "传感器",
    "拍摄"
  ],
  "280": [
    "债券",
    "债市",
    "债基",
    "基金",
    "降息"
  ],
  "281": [
    "黄蜂队",
    "丹普斯",
    "续约",
    "蜂王",
    "球员"
  ],
  "282": [
    "水怪",
    "深湖",
    "巨兽",
    "征文",
    "有奖"
  ],
  "283": [
    "人气",
    "最旺",
    "双倍",
    "美丽",
    "online"
  ],
  "284": [
    "福尔摩斯",
    "夏洛克",
    "唐尼",
    "罗伯特",
    "裘德"
  ],
  "285": [
    "职业",
    "刑天舞",
    "新服",
    "充值卡",
    "人气"
  ],
  "286": [
    "G3",
    "DSC",
    "分享",
    "功能",
    "拍摄"
  ],
  "287": [
    "乐园",
    "春耕",
    "耕耘",
    "帮会",
    "活动"
  ],
  "288": [
    "公会",
    "领地",
    "外交",
    "管理员",
    "成员"
  ],
  "289": [
    "专户",
    "交银",
    "QDII",
    "施罗德",
    "业务"
  ],
  "290": [
    "顾全",
    "东莞",
    "孟铎",
    "邱彪",
    "戈尔"
  ],
  "291": [
    "小牛",
    "脚踝",
    "T恤",
    "湖人",
    "训练"
  ],
  "292": [
    "分红",
    "基金",
    "张远忠",
    "基民",
    "兴业"
  ],
  "293": [
    "D90",
    "尼康",
    "支持",
    "接口",
    "功能"
  ],
  "294": [
    "华商",
    "型基金",
    "基金",
    "收益率",
    "业绩"
  ],
  "295": [
    "丹麦",
    "塞隆",
    "基德曼",
    "女孩",
    "女儿"
  ],
  "296": [
    "Studio2",
    "金基德",
    ".0",
    "Film",
    "电影"
  ],
  "297": [
    "D300S",
    "尼康",
    "单机",
    "旗舰",
    "中关村"
  ],
  "298": [
    "touch",
    "iPod",
    "苹果",
    "GB",
    "上网"
  ],
  "299": [
    "韩国",
    "电影周",
    "影院",
    "黄真伊",
    "密阳"
  ],
  "300": [
    "E30",
    "艾利和",
    "e30",
    "SRS",
    "WOW"
  ],
  "301": [
    "丹尼尔",
    "听歌",
    "敞篷车",
    "藉此",
    "歌舞片"
  ],
  "302": [
    "卡西欧",
    "畸变",
    "G1",
    "EX",
    "测试"
  ],
  "303": [
    "曼谷",
    "杀手",
    "北美票房",
    "Bangkok",
    "Dangerous"
  ],
  "304": [
    "英雄",
    "奥尼尔",
    "邓肯",
    "球迷",
    "魔术"
  ],
  "305": [
    "FE5020",
    "FE",
    "实用",
    "比长",
    "集成"
  ],
  "306": [
    "vs",
    "预测",
    "投下",
    "一票",
    "打响"
  ],
  "307": [
    "同性恋",
    "布洛迪",
    "德里",
    "角色",
    "Richie"
  ],
  "308": [
    "木乃伊",
    "李连杰",
    "中国",
    "元素",
    "观众"
  ],
  "309": [
    "基金",
    "股票",
    "增持",
    "比例",
    "减持"
  ],
  "310": [
    "天域",
    "记得",
    "感动",
    "友友",
    "春光明媚"
  ],
  "311": [
    "阴谋",
    "麦克斯",
    "亚利桑那",
    "波利斯",
    "建立"
  ],
  "312": [
    "三国演义",
    "历史",
    "激情",
    "时代",
    "汉延康"
  ],
  "313": [
    "莫雷",
    "火箭队",
    "选帅",
    "范甘迪",
    "亚历山大"
  ],
  "314": [
    "加索尔",
    "队友",
    "媒体",
    "谎言",
    "禅师"
  ],
  "315": [
    "哈夫利",
    "戴维斯",
    "比赛",
    "绿军",
    "波士顿"
  ],
  "316": [
    "航海",
    "漫画",
    "新春",
    "手机",
    "幽默"
  ],
  "317": [
    "基金",
    "行业",
    "年报",
    "券商",
    "投资"
  ],
  "318": [
    "结婚",
    "同心",
    "玩家",
    "礼券",
    "online"
  ],
  "319": [
    "酷柚",
    "地下城",
    "BOSS",
    "一撮",
    "残片"
  ],
  "320": [
    "伤情",
    "鲨鱼",
    "球员",
    "加重",
    "蓝图"
  ],
  "321": [
    "龙河",
    "金敏贞",
    "作战",
    "性感",
    "组图"
  ],
  "322": [
    "基金",
    "经理",
    "投资者",
    "能力",
    "基民"
  ],
  "323": [
    "武林",
    "愚人节",
    "武侠",
    "OL",
    "wl"
  ],
  "324": [
    "送转",
    "除权",
    "席位",
    "分红",
    "机构"
  ],
  "325": [
    "中海",
    "红利",
    "基金",
    "份额",
    "分红"
  ],
  "326": [
    "布雷克",
    "湖人",
    "外线",
    "三分",
    "篮筐"
  ],
  "327": [
    "IXUS200IS",
    "佳能",
    "触摸",
    "超广角",
    "对焦"
  ],
  "328": [
    "战役",
    "恶魔",
    "英雄",
    "格拉姆",
    "石像"
  ],
  "329": [
    "红名",
    "打扰",
    "玩家",
    "不能",
    "惩罚"
  ],
  "330": [
    "资产",
    "配置",
    "投资者",
    "风险",
    "比重"
  ],
  "331": [
    "湖人",
    "助攻",
    "小牛",
    "飞侠",
    "单场"
  ],
  "332": [
    "HF",
    "S100",
    "摄像机",
    "佳能",
    "FULL"
  ],
  "333": [
    "申购",
    "收益率",
    "大额",
    "取消",
    "泰达"
  ],
  "334": [
    "记者会",
    "贝尔",
    "蝙蝠侠",
    "出席",
    "赴美"
  ],
  "335": [
    "F75EXR",
    "富士",
    "变焦",
    "光学",
    "机身"
  ],
  "336": [
    "教练",
    "公牛",
    "希伯杜",
    "当选",
    "带领"
  ],
  "337": [
    "老鹰",
    "看待",
    "赛点",
    "本场",
    "公牛"
  ],
  "338": [
    "空间站",
    "iPod",
    "加利",
    "太空",
    "地球"
  ],
  "339": [
    "罗斯",
    "系列赛",
    "趣谈",
    "比赛",
    "闪电侠"
  ],
  "340": [
    "水啸",
    "雾都",
    "木乃伊",
    "伦敦",
    "宏大"
  ],
  "341": [
    "海富通",
    "中国",
    "分红",
    "精选",
    "基准"
  ],
  "342": [
    "波什",
    "热火",
    "詹姆斯",
    "韦德",
    "首轮"
  ],
  "343": [
    "梦工厂",
    "迪士尼",
    "协议",
    "签订",
    "发行"
  ],
  "344": [
    "信诚",
    "账户",
    "人寿保险",
    "得益",
    "信托"
  ],
  "345": [
    "v1",
    "单败",
    "淘汰赛",
    "比赛",
    "武林大会"
  ],
  "346": [
    "飞扬",
    "手机游戏",
    "企业",
    "楚留香",
    "中关村"
  ],
  "347": [
    "摔角",
    "金狮",
    "男主角",
    "奥斯卡",
    "脱衣舞娘"
  ],
  "348": [
    "木乃伊",
    "一票",
    "票房",
    "影片",
    "评分"
  ],
  "349": [
    "修改",
    "赤壁",
    "配方",
    "军饷",
    "间隔"
  ],
  "350": [
    "收益率",
    "基金",
    "国海",
    "富兰克林",
    "相差"
  ],
  "351": [
    "动物",
    "农场",
    "宫崎骏",
    "牲畜",
    "革命"
  ],
  "352": [
    "国泰",
    "双利",
    "全景网",
    "申购",
    "赎回"
  ],
  "353": [
    "罗斯",
    "公牛",
    "老鹰",
    "史密斯",
    "霍福德"
  ],
  "354": [
    "Johnny",
    "Sir",
    "杜琪峰",
    "奇谋",
    "强尼"
  ],
  "355": [
    "德利",
    "柏林",
    "朗读",
    "生死",
    "斯莱特"
  ],
  "356": [
    "贝鲁奇",
    "影展",
    "罗马",
    "莫妮卡",
    "得主"
  ],
  "357": [
    "三国",
    "印魂",
    "梦想",
    "设计者",
    "硝烟"
  ],
  "358": [
    "变形金刚",
    "预告片",
    "上线",
    "金刚",
    "首款"
  ],
  "359": [
    "湖人",
    "第二轮",
    "客场",
    "小牛",
    "5.1"
  ],
  "360": [
    "皮克斯",
    "飞屋",
    "游记",
    "海报",
    "立体电影"
  ],
  "361": [
    "朱迪",
    "嘉兰",
    "传记",
    "海瑟薇",
    "奥斯卡"
  ],
  "362": [
    "水怪",
    "深湖",
    "巨兽",
    "打捞",
    "潜艇"
  ],
  "363": [
    "格林",
    "安吉",
    "期望值",
    "适应",
    "球队"
  ],
  "364": [
    "DAL",
    "百元",
    "宾得",
    "KX",
    "一秒"
  ],
  "365": [
    "周琦",
    "效力",
    "身高",
    "选秀",
    "土耳其"
  ],
  "366": [
    "开放",
    "赤壁",
    "三国鼎立",
    "黄巾军",
    "魏国"
  ],
  "367": [
    "昌西",
    "尼克斯",
    "纽约",
    "合同",
    "薪金"
  ],
  "368": [
    "P1",
    "E",
    "可换",
    "单反相机",
    "镜头"
  ],
  "369": [
    "ST550",
    "三星",
    "震动",
    "拍摄",
    "115.2"
  ],
  "370": [
    "宠物",
    "宝贝",
    "技能",
    "商处",
    "国度"
  ],
  "371": [
    "长城",
    "景顺",
    "营销",
    "梁华栋",
    "梁氏"
  ],
  "372": [
    "F75EXR",
    "富士",
    "EXR",
    "Super",
    "F75"
  ],
  "373": [
    "SX60E",
    "索尼",
    "特惠",
    "郑州",
    "郑州市"
  ],
  "374": [
    "小牛",
    "三分球",
    "湖人",
    "跳投",
    "三分"
  ],
  "375": [
    "罗德曼",
    "夜总会",
    "大虫",
    "大寿",
    "风流"
  ],
  "376": [
    "外星人",
    "D",
    "怪兽",
    "宣传",
    "眼镜"
  ],
  "377": [
    "湖人",
    "谈到",
    "禅师",
    "节奏",
    "比赛"
  ],
  "378": [
    "东南",
    "协会",
    "SEFCA",
    "影评人",
    "第二名"
  ],
  "379": [
    "九州",
    "online",
    "再起",
    "风云",
    "道具"
  ],
  "380": [
    "宏远",
    "高管",
    "副总经理",
    "基金",
    "变动"
  ],
  "381": [
    "宝箱",
    "山洞",
    "结界",
    "小道",
    "返回"
  ],
  "382": [
    "工资",
    "摘星",
    "封神",
    "任务",
    "全额"
  ],
  "383": [
    "横扫",
    "湖人",
    "落后",
    "第四场",
    "翻盘"
  ],
  "384": [
    "绿衫",
    "热火",
    "交手",
    "詹姆斯",
    "习惯于"
  ],
  "385": [
    "小奥",
    "游戏城",
    "农场",
    "金花",
    "游戏"
  ],
  "386": [
    "公会",
    "成员",
    "团结",
    "会长",
    "发展"
  ],
  "387": [
    "万家",
    "基金",
    "精选",
    "品种",
    "个股"
  ],
  "388": [
    "帮派",
    "挑战赛",
    "网游",
    "帐号",
    "VIP"
  ],
  "389": [
    "D90",
    "尼康",
    "短片",
    "拍摄",
    "像素"
  ],
  "390": [
    "相像",
    "梅兰芳",
    "李准基",
    "韩星",
    "男人"
  ],
  "391": [
    "得手",
    "热火",
    "镁粉",
    "上篮",
    "詹姆斯"
  ],
  "392": [
    "荷银",
    "吴俊峰",
    "泰达",
    "合丰",
    "基金"
  ],
  "393": [
    "工资",
    "掉落",
    "情人节",
    "BOSS",
    "财富"
  ],
  "394": [
    "收益率",
    "债券",
    "券商",
    "产品",
    "平均"
  ],
  "395": [
    "魔术",
    "老鹰",
    "gt",
    "德鲁",
    "罗斯"
  ],
  "396": [
    "基金",
    "海富通",
    "亿元",
    "海通",
    "富国"
  ],
  "397": [
    "棒棒",
    "会员",
    "数字",
    "水晶",
    "回复"
  ],
  "398": [
    "折价率",
    "建信",
    "动力",
    "交易日",
    "救生艇"
  ],
  "399": [
    "利民",
    "女篮",
    "训练",
    "队员",
    "首钢"
  ],
  "400": [
    "蜀山",
    "剑侠",
    "战斗",
    "体验",
    "抢先"
  ],
  "401": [
    "下跌",
    "跌幅",
    "基指",
    "ETF",
    "股指"
  ],
  "402": [
    "智慧",
    "AUTO",
    "检测",
    "模式",
    "拍摄"
  ],
  "403": [
    "安娜",
    "助理",
    "女魔头",
    "VOGUE",
    "PRADA"
  ],
  "404": [
    "V6000HDK",
    "高清",
    "艾诺",
    "解码",
    "P"
  ],
  "405": [
    "史密斯",
    "德鲁",
    "老鹰",
    "封盖",
    "篮下"
  ],
  "406": [
    "拉伯",
    "洛克",
    "斯科特",
    "白痴",
    "老板"
  ],
  "407": [
    "仓位",
    "基金",
    "增仓",
    "上升",
    "减仓"
  ],
  "408": [
    "增持",
    "行业",
    "基金",
    "金融保险",
    "金融"
  ],
  "409": [
    "D90",
    "尼康",
    "短片",
    "拍摄",
    "镜头"
  ],
  "410": [
    "公主",
    "地中海",
    "巴伯",
    "uen",
    "土耳其"
  ],
  "411": [
    "天行",
    "海选",
    "tianxing",
    "女孩",
    "选拔赛"
  ],
  "412": [
    "杨采妮",
    "学校",
    "泰国",
    "坦言",
    "出席"
  ],
  "413": [
    "奢华",
    "家族",
    "成员",
    "棒棒",
    "回忆"
  ],
  "414": [
    "杰克逊",
    "执教",
    "禅师",
    "生涯",
    "湖人"
  ],
  "415": [
    "收益分配",
    "年度",
    "基金",
    "通乾",
    "全景网"
  ],
  "416": [
    "宣传片",
    "沙僧",
    "观音",
    "孙悟空",
    "悟空"
  ],
  "417": [
    "广角",
    "光学",
    "M420",
    "通体",
    "看下"
  ],
  "418": [
    "文明",
    "奖励",
    "名单",
    "宝宝",
    "活动"
  ],
  "419": [
    "基金",
    "中邮",
    "收益率",
    "华夏",
    "净值"
  ],
  "420": [
    "门派",
    "武林",
    "传送",
    "体贴",
    "OL"
  ],
  "421": [
    "绿军",
    "得手",
    "皮尔斯",
    "上篮",
    "拿下"
  ],
  "422": [
    "训练",
    "费舍尔",
    "湖人队",
    "禅师",
    "反省"
  ],
  "423": [
    "IMDB",
    "电影",
    "电视剧",
    "服务",
    "用户"
  ],
  "424": [
    "ZR1",
    "松下",
    "2.7",
    "英寸",
    "套装"
  ],
  "425": [
    "创业板",
    "基金",
    "市场",
    "资本",
    "分流"
  ],
  "426": [
    "l",
    "开放",
    "地图",
    "契约",
    "新城镇"
  ],
  "427": [
    "T900",
    "索尼",
    "原装",
    "卡片机",
    "促销"
  ],
  "428": [
    "杰克逊",
    "换下",
    "裁判",
    "录像",
    "抗议"
  ],
  "429": [
    "专户",
    "QDII",
    "施罗德",
    "业务",
    "首单"
  ],
  "430": [
    "黄蜂队",
    "湖人队",
    "第六场",
    "说道",
    "活力"
  ],
  "431": [
    "蝙蝠侠",
    "翁立",
    "引进",
    "内地",
    "大片"
  ],
  "432": [
    "新疆",
    "上海",
    "彭飞",
    "命中",
    "得手"
  ],
  "433": [
    "刘炜",
    "嘘声",
    "球迷",
    "陈磊",
    "遭到"
  ],
  "434": [
    "平均",
    "基金净值",
    "股票",
    "债券",
    "开放式"
  ],
  "435": [
    "佳能",
    "D",
    "EOS",
    "高精度",
    "测光"
  ],
  "436": [
    "系统",
    "房子",
    "结婚",
    "合宠",
    "家园"
  ],
  "437": [
    "修正",
    "BUG",
    "赔偿",
    "神契",
    "玩家"
  ],
  "438": [
    "章子怡",
    "骑士",
    "第二部",
    "上映",
    "北美"
  ],
  "439": [
    "公牛",
    "热火",
    "决赛",
    "芝加哥",
    "主场"
  ],
  "440": [
    "V5HD",
    "COWON",
    "播放",
    "GB",
    "新品"
  ],
  "441": [
    "斯彭斯",
    "摄像头",
    "义眼",
    "纪录片",
    "探讨"
  ],
  "442": [
    "神域",
    "OL",
    "封测",
    "玩家",
    "游戏"
  ],
  "443": [
    "老鹰",
    "公牛",
    "罗斯",
    "打法",
    "科林斯"
  ],
  "444": [
    "诛神",
    "落款",
    "online",
    "纸条",
    "假钞"
  ],
  "445": [
    "基德曼",
    "贵妇",
    "刘易斯",
    "丹尼尔",
    "造型"
  ],
  "446": [
    "武林",
    "武侠",
    "OL",
    "新区",
    "中华"
  ],
  "447": [
    "罗斯",
    "评价",
    "捧杯",
    "新科",
    "体面"
  ],
  "448": [
    "烙印",
    "PC",
    "网游",
    "游戏",
    "九九"
  ],
  "449": [
    "电影节",
    "俄罗斯",
    "闭幕式",
    "戏剧",
    "舞台"
  ],
  "450": [
    "基金",
    "投资",
    "漂移",
    "风格",
    "小盘"
  ],
  "451": [
    "龙珠",
    "七龙珠",
    "武昆",
    "电影",
    "成都"
  ],
  "452": [
    "中邮",
    "申购",
    "优选",
    "核心",
    "客户"
  ],
  "453": [
    "丹尼尔",
    "一集",
    "开拍",
    "海啸",
    "麦凯恩"
  ],
  "454": [
    "散户",
    "四只",
    "买入",
    "个股",
    "老鼠"
  ],
  "455": [
    "公牛",
    "罗斯",
    "MVP",
    "球队",
    "乔丹"
  ],
  "456": [
    "基金",
    "下跌",
    "净值",
    "成长型",
    "小盘"
  ],
  "457": [
    "复活节",
    "宝贝",
    "珍惜",
    "心痛",
    "象征"
  ],
  "458": [
    "股票",
    "型基金",
    "增长率",
    "基金",
    "业绩"
  ],
  "459": [
    "湖人",
    "蠢蛋",
    "集体",
    "忘掉",
    "搞怪"
  ],
  "460": [
    "金豆",
    "悬赏",
    "财宝",
    "大内",
    "盗贼"
  ],
  "461": [
    "XR100E",
    "索尼",
    "硬盘",
    "影像",
    "介质"
  ],
  "462": [
    "增幅",
    "净值",
    "单位",
    "基金",
    "型基金"
  ],
  "463": [
    "小奥",
    "游戏城",
    "金花",
    "界面",
    "中国象棋"
  ],
  "464": [
    "人品",
    "精灵",
    "口袋",
    "任务",
    "队长"
  ],
  "465": [
    "A2100",
    "佳能",
    "全自动",
    "MMCplus",
    "数码相机"
  ],
  "466": [
    "基金",
    "经理",
    "人才",
    "经理制",
    "基金业"
  ],
  "467": [
    "詹姆斯",
    "抛洒",
    "镁粉",
    "头发",
    "赢球"
  ],
  "468": [
    "M880",
    "忆捷",
    "BT",
    "解码",
    "下载"
  ],
  "469": [
    "小牛队",
    "取决于",
    "比赛",
    "湖人队",
    "保持"
  ],
  "470": [
    "信托",
    "指数",
    "评级",
    "净值",
    "基金"
  ],
  "471": [
    "获奖",
    "玫瑰花",
    "天域",
    "红五月",
    "奖励"
  ],
  "472": [
    "魔符",
    "取出",
    "九州",
    "奖励",
    "online"
  ],
  "473": [
    "伊巴",
    "马丁",
    "纳利",
    "劳森",
    "盖帽"
  ],
  "474": [
    "邓华德",
    "北京队",
    "上海队",
    "鲨鱼",
    "主动权"
  ],
  "475": [
    "对阵",
    "纪录",
    "魔术师",
    "安东尼",
    "另类"
  ],
  "476": [
    "灵兽",
    "试炼",
    "海盗",
    "世界",
    "三倍"
  ],
  "477": [
    "患上",
    "风趣",
    "严肃",
    "斯文",
    "痢疾"
  ],
  "478": [
    "基金",
    "披露",
    "经理",
    "孙延群",
    "信息"
  ],
  "479": [
    "天域",
    "年兽",
    "鞭炮",
    "热闹",
    "新春"
  ],
  "480": [
    "康利",
    "雷霆",
    "内线",
    "小康",
    "和威斯"
  ],
  "481": [
    "IS",
    "IXUS",
    "佳能",
    "IXUS990IS",
    "像素"
  ],
  "482": [
    "湖人队",
    "小牛队",
    "加索尔",
    "洛杉矶",
    "杰克逊"
  ],
  "483": [
    "D300S",
    "原厂",
    "DX",
    "尼康",
    "套机"
  ],
  "484": [
    "澳大利亚",
    "基德曼",
    "恶评",
    "生硬",
    "评分"
  ],
  "485": [
    "USB",
    "全世界",
    "9.99",
    "爱抚",
    "兼容"
  ],
  "486": [
    "巩俐",
    "飙戏",
    "救世军",
    "终结者",
    "布拉德"
  ],
  "487": [
    "专户",
    "交银",
    "施罗德",
    "QDII",
    "签署"
  ],
  "488": [
    "加索尔",
    "对抗",
    "激烈",
    "弟弟",
    "马克"
  ],
  "489": [
    "慈善",
    "基金会",
    "大成",
    "资助",
    "广东省"
  ],
  "490": [
    "游说",
    "武将",
    "口才",
    "将领",
    "霸业"
  ],
  "491": [
    "麦克戴斯",
    "职业生涯",
    "马刺",
    "圣安东尼奥",
    "退役"
  ],
  "492": [
    "灵侠",
    "章鱼",
    "预告片",
    "Jackson",
    "城市"
  ],
  "493": [
    "中小板",
    "基金",
    "交银",
    "先锋",
    "施罗德"
  ],
  "494": [
    "文明",
    "II",
    "奖励",
    "o",
    "玩家"
  ],
  "495": [
    "D3000",
    "尼康",
    "引导",
    "模式",
    "对焦"
  ],
  "496": [
    "小奥",
    "绿军",
    "刀锋战士",
    "科斯蒂",
    "来得"
  ],
  "497": [
    "热火",
    "韦德",
    "客场",
    "TD",
    "波士顿"
  ],
  "498": [
    "打响",
    "半决赛",
    "热血",
    "灰熊",
    "直播"
  ],
  "499": [
    "布莱尔",
    "克林顿",
    "女王",
    "两部",
    "三部曲"
  ],
  "500": [
    "募集",
    "基金",
    "份额",
    "19.94",
    "募近"
  ],
  "501": [
    "七匹狼",
    "万股",
    "股东",
    "增持",
    "基金"
  ],
  "502": [
    "老鹰",
    "公牛",
    "罗斯",
    "投篮",
    "洛尔"
  ],
  "503": [
    "C10",
    "三星",
    "套装",
    "具有",
    "像素"
  ],
  "504": [
    "S1500",
    "富士",
    "刘然",
    "位移",
    "长焦端"
  ],
  "505": [
    "万美元",
    "票房",
    "量子",
    "单日",
    "危机"
  ],
  "506": [
    "A175",
    "处为",
    "富士",
    "21.9",
    "最薄"
  ],
  "507": [
    "晶灵",
    "明王",
    "藏宝图",
    "称号",
    "不动"
  ],
  "508": [
    "华宝",
    "销售",
    "兴业",
    "上柜",
    "现金"
  ],
  "509": [
    "足球",
    "防火墙",
    "足坛",
    "行业",
    "打假"
  ],
  "510": [
    "金球奖",
    "选票",
    "推迟",
    "提名",
    "电视"
  ],
  "511": [
    "布泽",
    "罗斯",
    "批评",
    "卡洛斯",
    "脚趾"
  ],
  "512": [
    "查尔",
    "安东尼",
    "斯帅",
    "热火",
    "开场"
  ],
  "513": [
    "封神",
    "童子",
    "开封",
    "散财",
    "准时"
  ],
  "514": [
    "甄子丹",
    "版权",
    "启播",
    "徐小明",
    "促成"
  ],
  "515": [
    "S930",
    "索尼",
    "2.4",
    "机身",
    "时尚"
  ],
  "516": [
    "XD90",
    "纽曼",
    "录音",
    "电话",
    "长期保持"
  ],
  "517": [
    "海信",
    "投影",
    "K",
    "LED",
    "文件"
  ],
  "518": [
    "票房",
    "马利",
    "亿美元",
    "历史纪录",
    "万美元"
  ],
  "519": [
    "QDII",
    "净值",
    "基金",
    "1.32",
    "理财产品"
  ],
  "520": [
    "基指",
    "七个",
    "收盘",
    "基金",
    "开盘"
  ],
  "521": [
    "亚美",
    "雷欧",
    "梅丽莎",
    "玛雅",
    "贝蒂"
  ],
  "522": [
    "TG01",
    "屏幕",
    "HD2",
    "手机",
    "东芝"
  ],
  "523": [
    "湖人",
    "横扫",
    "魔咒",
    "NBA",
    "奇迹"
  ],
  "524": [
    "诸侯",
    "国战",
    "赤壁",
    "军团长",
    "国家"
  ],
  "525": [
    "iPhone",
    "掌机",
    "OS",
    "PSP",
    "苹果"
  ],
  "526": [
    "FX65",
    "松下",
    "光学",
    "机身",
    "mm"
  ],
  "527": [
    "佳能",
    "D",
    "套机",
    "通用性",
    "产品组合"
  ],
  "528": [
    "基金",
    "景顺",
    "建仓",
    "长城",
    "仓位"
  ],
  "529": [
    "疲劳",
    "再赢",
    "湖人",
    "浪费",
    "一年"
  ],
  "530": [
    "乐园",
    "男索",
    "休闲",
    "群聊",
    "O"
  ],
  "531": [
    "D90",
    "D80",
    "尼康",
    "保修",
    "D300"
  ],
  "532": [
    "基金",
    "动力",
    "资产",
    "核心",
    "代销"
  ],
  "533": [
    "万股",
    "基金",
    "流通股东",
    "华夏",
    "减持"
  ],
  "534": [
    "韦德",
    "查尔",
    "安东尼",
    "热火",
    "加内特"
  ],
  "535": [
    "伊巴",
    "盖帽",
    "内线",
    "封盖",
    "防守"
  ],
  "536": [
    "希特勒",
    "打分",
    "影视",
    "点评",
    "行动"
  ],
  "537": [
    "益民",
    "总经理",
    "宋瑞",
    "辞职",
    "职务"
  ],
  "538": [
    "愚人节",
    "宝贝",
    "新宠",
    "pri",
    "国度"
  ],
  "539": [
    "基金",
    "定期",
    "报告",
    "年报",
    "投资"
  ],
  "540": [
    "拿到",
    "第六",
    "禅师",
    "有点",
    "杰克逊"
  ],
  "541": [
    "湖人",
    "禁赛",
    "阿泰",
    "比赛",
    "处罚"
  ],
  "542": [
    "涨幅",
    "基金",
    "开放式",
    "型基金",
    "业绩"
  ],
  "543": [
    "佳能",
    "D",
    "用户",
    "不多",
    "旅游"
  ],
  "544": [
    "歌曲",
    "入围",
    "选手",
    "参赛",
    "名单"
  ],
  "545": [
    "D5000",
    "尼康",
    "翻转",
    "方便",
    "成像"
  ],
  "546": [
    "活动",
    "文明",
    "II",
    "累计",
    "玩家"
  ],
  "547": [
    "富士",
    "J26",
    "刘然",
    "百元",
    "风范"
  ],
  "548": [
    "佛山",
    "辽宁队",
    "马布里",
    "杨鸣",
    "李晓旭"
  ],
  "549": [
    "PMI",
    "长信",
    "经济",
    "宏观经济",
    "GDP"
  ],
  "550": [
    "基金",
    "华夏",
    "修改",
    "公告",
    "一章"
  ],
  "551": [
    "篮网",
    "留下",
    "愿意",
    "德隆",
    "补强"
  ],
  "552": [
    "下载",
    "千尺",
    "WiFi",
    "流量",
    "无线"
  ],
  "553": [
    "财神",
    "烧香",
    "敬香",
    "天问",
    "寺院"
  ],
  "554": [
    "上映",
    "赤壁",
    "澳洲",
    "中影集团",
    "赛车"
  ],
  "555": [
    "权相宇",
    "孙泰英",
    "孩子",
    "悲伤",
    "怀孕"
  ],
  "556": [
    "白色",
    "多元",
    "蕾丝",
    "长裙",
    "拼接"
  ],
  "557": [
    "小牛",
    "湖人",
    "洛城",
    "命中率",
    "可说"
  ],
  "558": [
    "龙珠",
    "神龙",
    "剧照",
    "传开",
    "灵通人士"
  ],
  "559": [
    "大陆",
    "加利",
    "水晶",
    "精灵",
    "完美"
  ],
  "560": [
    "可接",
    "活动",
    "灵兽",
    "任务",
    "经验"
  ],
  "561": [
    "朱利安",
    "更衣室",
    "大哥",
    "位置",
    "意思"
  ],
  "562": [
    "马刺",
    "犯规",
    "三分",
    "关头",
    "布置"
  ],
  "563": [
    "d",
    "赤壁",
    "春色",
    "美景",
    "阳春"
  ],
  "564": [
    "企图",
    "起诉",
    "警方",
    "律师",
    "蝙蝠侠"
  ],
  "565": [
    "帕克",
    "欧锦赛",
    "法国",
    "国家队",
    "马刺"
  ],
  "566": [
    "T900",
    "索尼",
    "卡片机",
    "促销",
    "摄像"
  ],
  "567": [
    "沃斯堡",
    "Next",
    "排名分",
    "富翁",
    "贫民"
  ],
  "568": [
    "密码",
    "毁灭",
    "地球",
    "亚历克斯",
    "罗亚斯"
  ],
  "569": [
    "车型",
    "时速",
    "HP",
    "赛车",
    "KM"
  ],
  "570": [
    "WB1000",
    "三星",
    "AMOLED",
    "防滑",
    "防抖"
  ],
  "571": [
    "澳大利亚",
    "基德曼",
    "粉丝",
    "纽约",
    "银幕"
  ],
  "572": [
    "篮板",
    "雷霆",
    "快攻",
    "包夹",
    "兰胖"
  ],
  "573": [
    "轩辕",
    "游戏",
    "元宣",
    "掌中",
    "蚩尤"
  ],
  "574": [
    "茱莉",
    "皮特",
    "主持人",
    "金球奖",
    "大道"
  ],
  "575": [
    "信托",
    "诺安",
    "基金",
    "深国投",
    "利益输送"
  ],
  "576": [
    "魔剑",
    "伊凡",
    "烙印",
    "启示录",
    "主角"
  ],
  "577": [
    "招聘",
    "渠道",
    "基金",
    "人才",
    "部门"
  ],
  "578": [
    "修正",
    "伙伴",
    "d",
    "军团",
    "降低"
  ],
  "579": [
    "神兆",
    "凌云",
    "一剑",
    "在于",
    "大门"
  ],
  "580": [
    "J",
    "档案",
    "制作",
    "上映",
    "情节"
  ],
  "581": [
    "时空",
    "公测",
    "OL",
    "亮点",
    "活动"
  ],
  "582": [
    "网游",
    "社交",
    "游戏",
    "K",
    "摩卡"
  ],
  "583": [
    "S220",
    "尼康",
    "纤巧",
    "洋红",
    "沾染"
  ],
  "584": [
    "礼包",
    "封神",
    "丰满",
    "碎片",
    "放送"
  ],
  "585": [
    "平民",
    "掘金",
    "步行者",
    "球队",
    "沃格尔"
  ],
  "586": [
    "ES15",
    "三星",
    "像素",
    "MAH",
    "数码"
  ],
  "587": [
    "天问",
    "城战",
    "团结",
    "城市",
    "有没有"
  ],
  "588": [
    "接口",
    "W",
    "P",
    "高清",
    "HTPC"
  ],
  "589": [
    "S230",
    "COOLPIX",
    "尼康",
    "尼克尔",
    "屏幕"
  ],
  "590": [
    "JVC",
    "MS100",
    "摄像机",
    "MS100AC",
    "GZ"
  ],
  "591": [
    "女儿国",
    "VIP",
    "掉落",
    "绿色",
    "天宫"
  ],
  "592": [
    "MOS",
    "松下",
    "元件",
    "感光",
    "需求"
  ],
  "593": [
    "ETF",
    "套利",
    "交易价格",
    "指数",
    "IOPV"
  ],
  "594": [
    "D",
    "佳能",
    "镜头",
    "IS",
    "爱好者"
  ],
  "595": [
    "热火",
    "面庞",
    "跳起",
    "三分",
    "传球"
  ],
  "596": [
    "宠物",
    "技能",
    "豪侠",
    "爱宠",
    "极品"
  ],
  "597": [
    "茱莉",
    "奥斯卡",
    "安吉丽娜",
    "暗战",
    "布莱德"
  ],
  "598": [
    "桑德勒",
    "海耶克",
    "萨尔玛",
    "鲁道夫",
    "玛雅"
  ],
  "599": [
    "泰信",
    "认购",
    "万元",
    "基金",
    "精选"
  ],
  "600": [
    "nano4",
    "iPod",
    "苹果",
    "Kbps",
    "AAC"
  ],
  "601": [
    "美人图",
    "预告片",
    "金敏善",
    "申尹福",
    "第二部"
  ],
  "602": [
    "游戏",
    "评分",
    "方向键",
    "父亲",
    "大侠"
  ],
  "603": [
    "涨幅",
    "型基金",
    "华商",
    "上扬",
    "0.01"
  ],
  "604": [
    "D",
    "摄影包",
    "套机",
    "佳能",
    "售价"
  ],
  "605": [
    "文明",
    "II",
    "活动",
    "玩家",
    "新春"
  ],
  "606": [
    "中邮",
    "仓位",
    "基金",
    "保德信",
    "海富通"
  ],
  "607": [
    "杜兰特",
    "雷霆",
    "掘金",
    "接球",
    "裁判"
  ],
  "608": [
    "星级",
    "转移",
    "刻印",
    "武林",
    "装备"
  ],
  "609": [
    "热火队",
    "波什",
    "凯队",
    "加内特",
    "戴维斯"
  ],
  "610": [
    "启示录",
    "制作",
    "豪华",
    "游戏",
    "新作"
  ],
  "611": [
    "亏损",
    "基金",
    "亏损额",
    "亿元",
    "型基金"
  ],
  "612": [
    "戒指",
    "伟大",
    "总冠军",
    "训练",
    "改变"
  ],
  "613": [
    "华特",
    "放屁",
    "法拉利",
    "和西恩",
    "出演"
  ],
  "614": [
    "WB550",
    "三星",
    "广角",
    "一枚",
    "镜头"
  ],
  "615": [
    "家伙",
    "观影",
    "韩国",
    "收回",
    "万名"
  ],
  "616": [
    "基金",
    "收益",
    "经理",
    "市场",
    "早报"
  ],
  "617": [
    "计划",
    "目标",
    "戒烟",
    "焦虑",
    "改掉"
  ],
  "618": [
    "公爵夫人",
    "安娜",
    "乔治",
    "英国",
    "宫廷"
  ],
  "619": [
    "康利",
    "依靠",
    "杜兰特",
    "三分球",
    "还魂"
  ],
  "620": [
    "CM3",
    "YP",
    "三星",
    "一台",
    "抽取"
  ],
  "621": [
    "礼品袋",
    "九州",
    "到达",
    "天龙八部",
    "玩家"
  ],
  "622": [
    "九州",
    "奖励",
    "精益求精",
    "online",
    "玩家"
  ],
  "623": [
    "D5000",
    "尼康",
    "手柄",
    "机身",
    "升级版"
  ],
  "624": [
    "演戏",
    "事业",
    "Bardot",
    "放弃",
    "可靠消息"
  ],
  "625": [
    "之躯",
    "谎言",
    "巴黎",
    "首映",
    "Body"
  ],
  "626": [
    "神戒",
    "Online",
    "充满",
    "内测",
    "wap2"
  ],
  "627": [
    "FE3010",
    "TruePicIII",
    "脸部",
    "优先",
    "输出"
  ],
  "628": [
    "银华",
    "和谐",
    "政策",
    "受益",
    "投资"
  ],
  "629": [
    "P90",
    "翻转",
    "尼康",
    "曝光",
    "覆盖范围"
  ],
  "630": [
    "吸血鬼",
    "全智贤",
    "海报",
    "上映",
    "英国"
  ],
  "631": [
    "EOS",
    "D",
    "单反相机",
    "像素",
    "画质"
  ],
  "632": [
    "柏林",
    "电影节",
    "梅兰芳",
    "金融危机",
    "大牌"
  ],
  "633": [
    "被盗",
    "哈尔滨",
    "能风",
    "原告",
    "黑龙江"
  ],
  "634": [
    "船舶",
    "产业",
    "基金",
    "投资",
    "王坤"
  ],
  "635": [
    "僵尸",
    "逍遥",
    "伤害",
    "林月如",
    "攻击"
  ],
  "636": [
    "泰信",
    "成长性",
    "蓝筹股",
    "精选",
    "认购"
  ],
  "637": [
    "风险",
    "基金",
    "配置",
    "活期储蓄",
    "节余"
  ],
  "638": [
    "EOS",
    "D",
    "像素",
    "画质",
    "感应器"
  ],
  "639": [
    "HD720QP",
    "监控器",
    "百万",
    "平安",
    "监控"
  ],
  "640": [
    "事故",
    "脑出血",
    "尸检",
    "救治",
    "医院"
  ],
  "641": [
    "阿巴斯",
    "上海队",
    "北京队",
    "篮筐",
    "老东家"
  ],
  "642": [
    "尼康",
    "D300S",
    "ISO",
    "影像",
    "相当于"
  ],
  "643": [
    "活动",
    "双城",
    "新春",
    "奖励",
    "集齐"
  ],
  "644": [
    "友邦",
    "华泰",
    "券商",
    "货币",
    "首只"
  ],
  "645": [
    "加索尔",
    "哥哥",
    "球队",
    "内线",
    "加时赛"
  ],
  "646": [
    "封基",
    "基金",
    "机构",
    "封闭式",
    "持有"
  ],
  "647": [
    "SR47E",
    "索尼",
    "DCR",
    "卡尔蔡",
    "大容量"
  ],
  "648": [
    "皮特",
    "佩洛西",
    "模范",
    "慈善",
    "国民"
  ],
  "649": [
    "恐怖",
    "电影",
    "Cult",
    "MTV",
    "经典"
  ],
  "650": [
    "奇顿",
    "公园",
    "编剧",
    "小说",
    "创作"
  ],
  "651": [
    "0.48",
    "红利",
    "全景网",
    "增强",
    "第十四次"
  ],
  "652": [
    "D3000",
    "尼康",
    "VR",
    "ISO",
    "套机"
  ],
  "653": [
    "山东队",
    "广东队",
    "江华",
    "连胜",
    "全队"
  ],
  "654": [
    "罗斯",
    "MVP",
    "公牛",
    "老鹰",
    "德鲁"
  ],
  "655": [
    "武林",
    "极品",
    "愚人",
    "饰品",
    "OL"
  ],
  "656": [
    "纳税",
    "百强",
    "综合",
    "基金",
    "年度"
  ],
  "657": [
    "利率",
    "投资人",
    "中央财政",
    "惠及",
    "工程"
  ],
  "658": [
    "经济",
    "宽松",
    "货币政策",
    "经理",
    "货币"
  ],
  "659": [
    "D",
    "佳能",
    "测光",
    "机身",
    "手柄"
  ],
  "660": [
    "GX200",
    "mm",
    "1.88",
    "X",
    "摄影"
  ],
  "661": [
    "纽曼",
    "商业",
    "好莱坞",
    "光影",
    "下列"
  ],
  "662": [
    "基金",
    "经理",
    "经济",
    "有色",
    "地产"
  ],
  "663": [
    "火箭队",
    "洛瑞",
    "莫雷",
    "顺位",
    "迷信"
  ],
  "664": [
    "神契",
    "系统",
    "ps",
    "online",
    "魔法"
  ],
  "665": [
    "黄蜂队",
    "湖人队",
    "内线",
    "说道",
    "进攻"
  ],
  "666": [
    "帕丁森",
    "罗伯特",
    "否认",
    "广告牌",
    "头部"
  ],
  "667": [
    "下跌",
    "跌幅",
    "ETF",
    "开盘",
    "低开"
  ],
  "668": [
    "利民",
    "队员",
    "处罚",
    "沟通",
    "年轻"
  ],
  "669": [
    "悲梦",
    "金导",
    "片子",
    "导演",
    "表达"
  ],
  "670": [
    "灵兽",
    "合成",
    "任务",
    "宝宝",
    "图谱"
  ],
  "671": [
    "S630",
    "尼康",
    "按钮",
    "配件",
    "超薄"
  ],
  "672": [
    "申购",
    "万元",
    "限额",
    "单日",
    "华夏"
  ],
  "673": [
    "脚踝",
    "第五场",
    "信任",
    "比赛",
    "倔强"
  ],
  "674": [
    "LOF",
    "认购",
    "指数",
    "基金",
    "跟踪"
  ],
  "675": [
    "克鲁斯",
    "游客",
    "影片",
    "The",
    "希特勒"
  ],
  "676": [
    "恶意",
    "犯规",
    "失望",
    "尴尬",
    "谈到"
  ],
  "677": [
    "认购",
    "基金",
    "力源",
    "液压",
    "动用"
  ],
  "678": [
    "仓位",
    "监测",
    "减仓",
    "基金",
    "上升"
  ],
  "679": [
    "军阶",
    "封神",
    "双倍",
    "降临",
    "极品"
  ],
  "680": [
    "奖金",
    "澳洲",
    "希斯",
    "设立",
    "评审"
  ],
  "681": [
    "老鹰",
    "公牛",
    "赛程",
    "辛里奇",
    "东区"
  ],
  "682": [
    "乐园",
    "世博",
    "O",
    "休闲",
    "多多"
  ],
  "683": [
    "M39",
    "格式",
    "播放",
    "接收",
    "支持"
  ],
  "684": [
    "热火",
    "直播室",
    "直播",
    "视频",
    "比赛"
  ],
  "685": [
    "宾得",
    "x",
    "K",
    "限量版",
    "白色"
  ],
  "686": [
    "LUX",
    "D",
    "松下",
    "LUX4",
    "使用者"
  ],
  "687": [
    "黑皮",
    "范霍文",
    "多部",
    "影片",
    "营救"
  ],
  "688": [
    "金荷娜",
    "抄袭",
    "海报",
    "夫妇",
    "公务员"
  ],
  "689": [
    "涨幅",
    "型基金",
    "口径",
    "基金",
    "业绩"
  ],
  "690": [
    "诅咒",
    "箱子",
    "九州",
    "online",
    "玩家"
  ],
  "691": [
    "黄蜂",
    "湖人",
    "得手",
    "内利",
    "投中"
  ],
  "692": [
    "金球",
    "奥斯卡",
    "金球奖",
    "影帝",
    "提名"
  ],
  "693": [
    "老鹰",
    "公牛",
    "未能",
    "罗斯",
    "布泽尔"
  ],
  "694": [
    "天赋",
    "神契",
    "技能",
    "德鲁伊",
    "大陆"
  ],
  "695": [
    "基金",
    "亿元",
    "规模",
    "募集",
    "民生"
  ],
  "696": [
    "PL70",
    "三星",
    "场景",
    "智能",
    "配有"
  ],
  "697": [
    "雷霆",
    "主场",
    "找回",
    "状态",
    "手感"
  ],
  "698": [
    "尼康",
    "D90",
    "套机",
    "清洁",
    "VR"
  ],
  "699": [
    "影城",
    "观众",
    "皇家",
    "赌场",
    "零点"
  ],
  "700": [
    "周星驰",
    "龙珠",
    "意见",
    "星爷",
    "监制"
  ],
  "701": [
    "S230",
    "尼康",
    "保护膜",
    "触控",
    "时尚"
  ],
  "702": [
    "ST10",
    "三星",
    "消费者",
    "套装",
    "新式"
  ],
  "703": [
    "秘鲁",
    "梅兰芳",
    "金熊奖",
    "伤心",
    "奶水"
  ],
  "704": [
    "经理",
    "基金",
    "孙延群",
    "摩根",
    "总监"
  ],
  "705": [
    "支付",
    "第三方",
    "汇付",
    "三方",
    "基金"
  ],
  "706": [
    "林志玲",
    "佛利",
    "武士",
    "男星",
    "新力"
  ],
  "707": [
    "加索尔",
    "球队",
    "批评",
    "湖人队",
    "沮丧"
  ],
  "708": [
    "规则",
    "篮联",
    "干扰",
    "斯特恩",
    "国际"
  ],
  "709": [
    "幻想",
    "明珠",
    "装备",
    "打造",
    "神兵"
  ],
  "710": [
    "专辑",
    "妓女",
    "歌舞片",
    "电影",
    "合唱"
  ],
  "711": [
    "基金",
    "经理",
    "业绩",
    "两只",
    "管理"
  ],
  "712": [
    "丹皮尔",
    "脚踝",
    "Z",
    "训练",
    "热火"
  ],
  "713": [
    "仓位",
    "基金",
    "季度",
    "行业",
    "A股"
  ],
  "714": [
    "D700",
    "尼康",
    "画幅",
    "侦测",
    "三脚架"
  ],
  "715": [
    "提名",
    "票房",
    "富翁",
    "贫民",
    "入围"
  ],
  "716": [
    "乐园",
    "O",
    "换上",
    "休闲",
    "一起"
  ],
  "717": [
    "御制",
    "适合",
    "装备",
    "治疗",
    "法术"
  ],
  "718": [
    "Z2",
    "卡西欧",
    "京东",
    "促销价",
    "变焦"
  ],
  "719": [
    "融通",
    "老鼠",
    "冷机",
    "周蔷",
    "散户"
  ],
  "720": [
    "基金",
    "银华",
    "和谐",
    "陆文俊",
    "管理部"
  ],
  "721": [
    "W290",
    "索尼",
    "Cetan",
    "W170",
    "整洁"
  ],
  "722": [
    "R8",
    "理光",
    "7.1",
    "复古",
    "照片"
  ],
  "723": [
    "竞争",
    "分红",
    "优势",
    "巴黎",
    "申万"
  ],
  "724": [
    "金城武",
    "怪人",
    "面相",
    "日本",
    "二十"
  ],
  "725": [
    "年度",
    "0.054",
    "基金",
    "收益分配",
    "全景网"
  ],
  "726": [
    "Z33WP",
    "富士",
    "夜景",
    "在行",
    "一族"
  ],
  "727": [
    "J26",
    "富士",
    "全景",
    "功能",
    "数码相机"
  ],
  "728": [
    "华纳公司",
    "法官",
    "纪录片",
    "后继有人",
    "控方"
  ],
  "729": [
    "碰上",
    "公牛",
    "热火",
    "卫冕冠军",
    "湖人"
  ],
  "730": [
    "德克",
    "麦克马洪",
    "成功率",
    "关键",
    "关键时刻"
  ],
  "731": [
    "基金",
    "万科",
    "A",
    "中国",
    "金元"
  ],
  "732": [
    "A股",
    "IPO",
    "投资",
    "私募",
    "市盈率"
  ],
  "733": [
    "d",
    "赤壁",
    "免费送",
    "诸侯",
    "OL"
  ],
  "734": [
    "S40",
    "思歌",
    "输出",
    "HDMI",
    "P"
  ],
  "735": [
    "口袋",
    "精灵",
    "元宝",
    "kdjl",
    "le"
  ],
  "736": [
    "训练场",
    "热火",
    "哈达威",
    "莫宁",
    "训练"
  ],
  "737": [
    "小奥",
    "游戏城",
    "农作物",
    "种田",
    "同胞"
  ],
  "738": [
    "海顿",
    "埃夫隆",
    "金球奖",
    "明星",
    "Heroes"
  ],
  "739": [
    "App",
    "Store",
    "Refenes",
    "开发者",
    "游戏"
  ],
  "740": [
    "宝宝",
    "怀孕",
    "赤壁",
    "d",
    "OL"
  ],
  "741": [
    "充值",
    "精灵",
    "口袋",
    "活动",
    "宠物"
  ],
  "742": [
    "总监",
    "基金",
    "投资",
    "管理",
    "业绩"
  ],
  "743": [
    "牛魔王",
    "铁扇公主",
    "爱情",
    "女性",
    "男人"
  ],
  "744": [
    "惨败",
    "调查",
    "筹码",
    "湖人",
    "袭击"
  ],
  "745": [
    "Rain",
    "片酬",
    "亿韩元",
    "好莱坞",
    "忍者"
  ],
  "746": [
    "EOS",
    "D",
    "感应器",
    "对焦",
    "自动"
  ],
  "747": [
    "昂达",
    "VX575HD",
    "MKV",
    "视频格式",
    "GB"
  ],
  "748": [
    "海通",
    "基金",
    "行业",
    "增持",
    "证券"
  ],
  "749": [
    "优惠",
    "直销",
    "费率",
    "渠道",
    "基金"
  ],
  "750": [
    "u1070",
    "卡片",
    "性价",
    "滑盖",
    "养眼"
  ],
  "751": [
    "经济",
    "经理",
    "投资",
    "基金",
    "年报"
  ],
  "752": [
    "小棒",
    "社区",
    "可爱",
    "棒棒",
    "好友"
  ],
  "753": [
    "分红",
    "红利",
    "基金",
    "派发",
    "登记日"
  ],
  "754": [
    "SNS",
    "MMO",
    "游戏",
    "游记",
    "网络游戏"
  ],
  "755": [
    "恶魔",
    "灵兽",
    "小时",
    "图谱",
    "护符"
  ],
  "756": [
    "押运",
    "三国",
    "明珠",
    "押送",
    "国家"
  ],
  "757": [
    "群雄",
    "天问",
    "公会",
    "帮派",
    "争霸赛"
  ],
  "758": [
    "感谢上帝",
    "抓到",
    "雷霆",
    "主场",
    "霍林斯"
  ],
  "759": [
    "Z33WP",
    "富士",
    "照片",
    "防水",
    "回放"
  ],
  "760": [
    "帮派",
    "三国",
    "印魂",
    "争霸",
    "团结"
  ],
  "761": [
    "佳能",
    "Mark",
    "画幅",
    "II",
    "尺寸"
  ],
  "762": [
    "国海",
    "富兰克林",
    "强化",
    "万元",
    "旗下"
  ],
  "763": [
    "邓肯",
    "马刺",
    "石佛",
    "无法",
    "比赛"
  ],
  "764": [
    "松下",
    "LX3GK",
    "模式",
    "LX3",
    "超广角"
  ],
  "765": [
    "基金",
    "折价率",
    "封闭式",
    "机构",
    "分红"
  ],
  "766": [
    "车站",
    "回家",
    "感动",
    "家乡",
    "行李"
  ],
  "767": [
    "iriver",
    "P7",
    "MPEG",
    "播放器",
    "视频"
  ],
  "768": [
    "奥斯卡",
    "主持",
    "主持人",
    "宣传照",
    "收视率"
  ],
  "769": [
    "私募",
    "企业",
    "吴克忠",
    "基金",
    "海涛"
  ],
  "770": [
    "时空",
    "冲级",
    "洗点",
    "钟情",
    "双倍"
  ],
  "771": [
    "红利",
    "分配",
    "成立",
    "金鹰",
    "分红"
  ],
  "772": [
    "Card",
    "纽曼",
    "Super",
    "NUNU",
    "GB"
  ],
  "773": [
    "分红",
    "基金",
    "通乾",
    "收益分配",
    "年度"
  ],
  "774": [
    "大奖",
    "阶数",
    "新区",
    "d",
    "赤壁"
  ],
  "775": [
    "爱国者",
    "MP5909HD",
    "播放",
    "4.3",
    "GB"
  ],
  "776": [
    "佣金",
    "券商",
    "中金公司",
    "亿元",
    "交易"
  ],
  "777": [
    "管理费",
    "规模",
    "资产",
    "收入",
    "基金"
  ],
  "778": [
    "上赛季",
    "薪金",
    "万美元",
    "球队",
    "姚明"
  ],
  "779": [
    "PM5927",
    "密钥",
    "爱国者",
    "月牙",
    "锁定"
  ],
  "780": [
    "阿童木",
    "铁臂",
    "意马",
    "机器人",
    "电影版"
  ],
  "781": [
    "广末凉子",
    "松本",
    "清张",
    "推理",
    "日本"
  ],
  "782": [
    "帮会",
    "宝石",
    "侠义",
    "人数",
    "帮派"
  ],
  "783": [
    "总分",
    "选票",
    "一队",
    "入选",
    "第一"
  ],
  "784": [
    "开户数",
    "回落",
    "万户",
    "基金",
    "四成"
  ],
  "785": [
    "电影节",
    "柏林",
    "开幕",
    "德国",
    "主席"
  ],
  "786": [
    "告负",
    "系列赛",
    "湖人队",
    "拿下",
    "首场"
  ],
  "787": [
    "交易所",
    "基金",
    "申购",
    "银行",
    "赎回费"
  ],
  "788": [
    "S90",
    "佳能",
    "PowerShot",
    "小巧",
    "锐利"
  ],
  "789": [
    "安吉",
    "波士顿",
    "绿衫",
    "留下",
    "斗志"
  ],
  "790": [
    "IXUS",
    "IS",
    "场景",
    "曝光",
    "对焦"
  ],
  "791": [
    "S70",
    "尼康",
    "OLED",
    "潜望",
    "3.5"
  ],
  "792": [
    "Hari",
    "印度",
    "Puttar",
    "哈利",
    "波特"
  ],
  "793": [
    "EOS",
    "D",
    "感应器",
    "对焦",
    "自动"
  ],
  "794": [
    "IXUS200IS",
    "光变",
    "FPS",
    "五倍",
    "佳能"
  ],
  "795": [
    "诛神",
    "新服",
    "光石",
    "online",
    "邓婵玉"
  ],
  "796": [
    "酒井法子",
    "梦墙",
    "日本",
    "恐吓",
    "张加贝"
  ],
  "797": [
    "游戏",
    "宠物",
    "按键",
    "数字",
    "操作"
  ],
  "798": [
    "入殓",
    "死者",
    "木雅弘",
    "仪式",
    "死亡"
  ],
  "799": [
    "手机游戏",
    "互联网",
    "移动",
    "应用",
    "易观"
  ],
  "800": [
    "GRDIII",
    "理光",
    "GRD",
    "VGA",
    "传感器"
  ],
  "801": [
    "卡戴珊",
    "太太",
    "湖人",
    "妻子",
    "不和"
  ],
  "802": [
    "信达",
    "澳银",
    "募集",
    "11.4",
    "亿元"
  ],
  "803": [
    "基金",
    "规模",
    "成立",
    "亿元",
    "募集"
  ],
  "804": [
    "B30",
    "音质",
    "纯音乐",
    "播放",
    "天籁"
  ],
  "805": [
    "选秀",
    "抽签",
    "雄鹿",
    "顺位",
    "乐透"
  ],
  "806": [
    "VX333",
    "昂达",
    "MP3",
    "纯音乐",
    "音质"
  ],
  "807": [
    "李安",
    "伍德斯",
    "伊美妲",
    "音乐节",
    "预告"
  ],
  "808": [
    "H20",
    "十倍",
    "摄像",
    "全手动",
    "光学"
  ],
  "809": [
    "IXUS",
    "IS",
    "佳能",
    "场景",
    "续航"
  ],
  "810": [
    "季票",
    "黄蜂",
    "销量",
    "球队",
    "所有权"
  ],
  "811": [
    "泰森",
    "莫里斯",
    "凯瑞",
    "同性恋",
    "圣丹斯"
  ],
  "812": [
    "IXUS",
    "佳能",
    "IS",
    "机身",
    "IXUS100IS"
  ],
  "813": [
    "经济",
    "经济学家",
    "数据",
    "市场",
    "刺激"
  ],
  "814": [
    "怪兽",
    "基弗",
    "卡赞",
    "伯格",
    "梦工厂"
  ],
  "815": [
    "强化",
    "侦探",
    "游戏",
    "装备",
    "伏龙"
  ],
  "816": [
    "忍者神龟",
    "真人",
    "动画",
    "皮特",
    "电脑"
  ],
  "817": [
    "J26",
    "富士",
    "场景",
    "识别",
    "2.7"
  ],
  "818": [
    "决赛",
    "老鹰",
    "相遇",
    "公牛",
    "热火"
  ],
  "819": [
    "雷霆",
    "得分手",
    "改打",
    "控卫",
    "助攻"
  ],
  "820": [
    "走步",
    "詹姆斯",
    "右脚",
    "跳步",
    "疑似"
  ],
  "821": [
    "阵营",
    "世界大战",
    "弗埃",
    "幻想",
    "明珠"
  ],
  "822": [
    "吕克",
    "贝松",
    "韩国",
    "秦始皇",
    "电影"
  ],
  "823": [
    "BP",
    "FS200",
    "品胜",
    "SANDISK",
    "Video"
  ],
  "824": [
    "老鹰",
    "公牛",
    "两队",
    "本场",
    "沿用"
  ],
  "825": [
    "帮派",
    "建设",
    "扣除",
    "上限",
    "人数"
  ],
  "826": [
    "ST",
    "中钨",
    "专户",
    "流通股",
    "银瑞信"
  ],
  "827": [
    "交通",
    "五洲",
    "股东",
    "转债",
    "万股"
  ],
  "828": [
    "奖提名",
    "朗读",
    "革命",
    "艺术",
    "指导"
  ],
  "829": [
    "豪侠",
    "梁山",
    "系统",
    "引导",
    "加强"
  ],
  "830": [
    "基金",
    "分红",
    "降息",
    "风险",
    "行业"
  ],
  "831": [
    "电影节",
    "柏林",
    "章子怡",
    "影片",
    "开幕"
  ],
  "832": [
    "猎手",
    "狙魔",
    "属性",
    "伤害",
    "敏捷"
  ],
  "833": [
    "格林",
    "绿军",
    "热火",
    "绿衫",
    "替补"
  ],
  "834": [
    "布鲁斯",
    "违约",
    "三家",
    "代理律师",
    "诉讼"
  ],
  "835": [
    "基金",
    "回暖",
    "流入",
    "收益率",
    "市场"
  ],
  "836": [
    "怡富",
    "章硕麟",
    "董事",
    "股份",
    "证券"
  ],
  "837": [
    "票房",
    "量子",
    "危机",
    "院线",
    "成绩"
  ],
  "838": [
    "宝贝",
    "快乐",
    "心情",
    "装扮",
    "客服"
  ],
  "839": [
    "型基金",
    "涨幅",
    "指数",
    "基金",
    "优选"
  ],
  "840": [
    "高跟鞋",
    "旱冰鞋",
    "朱莉",
    "走路",
    "安吉丽娜"
  ],
  "841": [
    "敌人",
    "武器",
    "伤害",
    "技能",
    "盾牌"
  ],
  "842": [
    "郭士强",
    "辽宁队",
    "比赛",
    "自信",
    "贺天举"
  ],
  "843": [
    "湖人队",
    "小牛队",
    "加索尔",
    "内线",
    "马里昂"
  ],
  "844": [
    "结转",
    "增利",
    "基金",
    "份额",
    "收益"
  ],
  "845": [
    "血魂",
    "骑士",
    "属性",
    "体质",
    "防御"
  ],
  "846": [
    "湖人",
    "霍华德",
    "费舍尔",
    "湖人队",
    "清洗"
  ],
  "847": [
    "金枪",
    "詹姆斯",
    "铁金刚",
    "丹尼尔",
    "手枪"
  ],
  "848": [
    "福尔摩斯",
    "唐尼",
    "罗伯特",
    "接下",
    "了盖"
  ],
  "849": [
    "XR500E",
    "索尼",
    "影像",
    "硬盘",
    "产品"
  ],
  "850": [
    "D5000",
    "尼康",
    "翻转",
    "带票",
    "六千"
  ],
  "851": [
    "金雅",
    "中将",
    "礼物",
    "烦恼",
    "重返"
  ],
  "852": [
    "斯马特",
    "勇士",
    "汤普森",
    "下课",
    "主帅"
  ],
  "853": [
    "梦工厂",
    "宝莱坞",
    "印度",
    "合作",
    "出资"
  ],
  "854": [
    "剪辑",
    "音效",
    "The",
    "提名",
    "工会"
  ],
  "855": [
    "绑定",
    "诸侯",
    "传送",
    "界面",
    "玉树"
  ],
  "856": [
    "老鹰",
    "罗斯",
    "公牛",
    "命中",
    "史密斯"
  ],
  "857": [
    "E520",
    "E",
    "TruePic",
    "实用功能",
    "MOS"
  ],
  "858": [
    "韦德",
    "阿伦",
    "闪电侠",
    "篮下",
    "绿军"
  ],
  "859": [
    "理财",
    "超越",
    "长江",
    "基金",
    "FOF"
  ],
  "860": [
    "巴恩斯",
    "T恤",
    "杰克逊",
    "比赛",
    "良性"
  ],
  "861": [
    "张惟闵",
    "富兰克林",
    "国海",
    "基金",
    "邓普顿"
  ],
  "862": [
    "斯帅",
    "热火",
    "丹皮尔",
    "阵容",
    "Z"
  ],
  "863": [
    "布尔",
    "性感",
    "女神",
    "巴铎",
    "碧姬"
  ],
  "864": [
    "ETF",
    "行业",
    "基金",
    "指数",
    "套利"
  ],
  "865": [
    "霍华德",
    "马刺",
    "魔术",
    "理由",
    "火箭"
  ],
  "866": [
    "巨头",
    "防守",
    "球队",
    "凯队",
    "波什"
  ],
  "867": [
    "热火",
    "领先",
    "首轮",
    "韦德",
    "季后赛"
  ],
  "868": [
    "基金",
    "成立",
    "兴业",
    "分红",
    "股票"
  ],
  "869": [
    "基金",
    "仓位",
    "重仓股",
    "公司",
    "增长率"
  ],
  "870": [
    "女儿国",
    "小青",
    "王者",
    "徒弟",
    "呵呵"
  ],
  "871": [
    "G3",
    "索尼",
    "DSC",
    "新鲜感",
    "浏览器"
  ],
  "872": [
    "马刺",
    "邓肯",
    "第四节",
    "霸道",
    "左手"
  ],
  "873": [
    "末路",
    "殖民",
    "动作",
    "明智",
    "越南"
  ],
  "874": [
    "D90",
    "尼康",
    "对焦",
    "D80",
    "取景器"
  ],
  "875": [
    "基金",
    "回报率",
    "业绩",
    "排名",
    "分化"
  ],
  "876": [
    "九州",
    "壮志凌云",
    "online",
    "新区",
    "开启"
  ],
  "877": [
    "时空",
    "双倍",
    "商城",
    "经验",
    "压测"
  ],
  "878": [
    "篮板",
    "评价",
    "胜绿军",
    "总分",
    "热火"
  ],
  "879": [
    "布雷克",
    "湖人队",
    "基德",
    "弱化",
    "小牛队"
  ],
  "880": [
    "武林",
    "门派",
    "武侠",
    "OL",
    "wl"
  ],
  "881": [
    "S640",
    "尼康",
    "支持",
    "文件",
    "光学"
  ],
  "882": [
    "M7",
    "韩元",
    "Opera",
    "无线",
    "GB"
  ],
  "883": [
    "战线",
    "七龙珠",
    "罗马",
    "澳大利亚",
    "协会"
  ],
  "884": [
    "B5",
    "酷比",
    "G",
    "魔方",
    "MP3"
  ],
  "885": [
    "T1",
    "BOSS",
    "图纸",
    "副本",
    "英杰"
  ],
  "886": [
    "加内特",
    "波什",
    "防守",
    "KG",
    "成绩"
  ],
  "887": [
    "回报率",
    "基金",
    "加权",
    "亿份",
    "大成"
  ],
  "888": [
    "公牛",
    "罗斯",
    "老鹰",
    "进攻",
    "希柏杜"
  ],
  "889": [
    "A480",
    "佳能",
    "博秀",
    "书脊",
    "PowerShot"
  ],
  "890": [
    "FZ28",
    "松下",
    "FZ18",
    "扩到",
    "率为"
  ],
  "891": [
    "股指",
    "市场",
    "吹泡泡",
    "转暖",
    "基金"
  ],
  "892": [
    "微软",
    "iPhone",
    "移植",
    "Windows",
    "Novell"
  ],
  "893": [
    "收视率",
    "奥斯卡",
    "娱乐节目",
    "颁奖典礼",
    "ABC"
  ],
  "894": [
    "流通股",
    "ST",
    "股东",
    "S",
    "万股"
  ],
  "895": [
    "费尔",
    "霍芬",
    "本能",
    "新作",
    "情色"
  ],
  "896": [
    "礼盒",
    "饺子",
    "炮竹",
    "封神",
    "兑换"
  ],
  "897": [
    "景顺",
    "长城",
    "基金",
    "询价",
    "长城公司"
  ],
  "898": [
    "电影节",
    "马克",
    "成都",
    "四川",
    "主席"
  ],
  "899": [
    "杜兰特",
    "掘金",
    "雷霆",
    "第一站",
    "回场"
  ],
  "900": [
    "歌舞",
    "青春",
    "毕业",
    "Troy",
    "狮子"
  ],
  "901": [
    "献唱",
    "哈德森",
    "公众",
    "阴影",
    "美国"
  ],
  "902": [
    "S2000HD",
    "位移",
    "防抖",
    "摄像",
    "图像"
  ],
  "903": [
    "颁奖礼",
    "奥斯卡",
    "收视率",
    "午宴",
    "大胆"
  ],
  "904": [
    "隆多",
    "左臂",
    "热火",
    "助攻",
    "森林狼"
  ],
  "905": [
    "基金",
    "收益分配",
    "分配",
    "分红",
    "通乾"
  ],
  "906": [
    "朱莉",
    "通缉犯",
    "海报",
    "英国",
    "皮特"
  ],
  "907": [
    "神域",
    "OL",
    "内测",
    "玩家",
    "yu"
  ],
  "908": [
    "赎回",
    "亿份",
    "申购",
    "基金",
    "份额"
  ],
  "909": [
    "漫画",
    "海报",
    "守望者",
    "阿克曼",
    "行头"
  ],
  "910": [
    "俄克拉荷马",
    "雷霆",
    "双方",
    "移师",
    "不变"
  ],
  "911": [
    "制作",
    "学习",
    "制造",
    "武器",
    "物品"
  ],
  "912": [
    "韦德",
    "詹姆斯",
    "人们",
    "热火",
    "总冠军"
  ],
  "913": [
    "权相宇",
    "MV",
    "悲伤",
    "礼服",
    "怀孕"
  ],
  "914": [
    "五一",
    "宝贝",
    "休闲",
    "song",
    "梦网"
  ],
  "915": [
    "热火",
    "韦德",
    "皮尔斯",
    "詹姆斯",
    "得手"
  ],
  "916": [
    "老鹰",
    "公牛",
    "罗斯",
    "原班",
    "激斗"
  ],
  "917": [
    "佳能",
    "D",
    "像素",
    "材料",
    "机降"
  ],
  "918": [
    "梅兰芳",
    "陈凯歌",
    "陈红",
    "女人",
    "晚装"
  ],
  "919": [
    "虎车",
    "充值",
    "惦记着",
    "送给",
    "魔币"
  ],
  "920": [
    "韦德",
    "斯帅",
    "首场",
    "挑事",
    "篮球比赛"
  ],
  "921": [
    "主席",
    "单元",
    "评审",
    "佩雷",
    "贝利亚"
  ],
  "922": [
    "M80HD",
    "ICOO",
    "本机",
    "播放",
    "兼容"
  ],
  "923": [
    "R10",
    "理光",
    "水平仪",
    "拍摄",
    "7.1"
  ],
  "924": [
    "管理费",
    "基金",
    "费率",
    "亏损",
    "公募"
  ],
  "925": [
    "仓位",
    "基金",
    "百分点",
    "季度",
    "季度末"
  ],
  "926": [
    "希斯",
    "Matilda",
    "保险公司",
    "保险金",
    "纳奥米"
  ],
  "927": [
    "范甘迪",
    "邀约",
    "农工",
    "出山",
    "德州"
  ],
  "928": [
    "开发者",
    "Android",
    "the",
    "Google",
    "Droid"
  ],
  "929": [
    "SX200IS",
    "佳能",
    "MMCplus",
    "具备",
    "像素"
  ],
  "930": [
    "德鲁",
    "史密斯",
    "老鹰",
    "罗斯",
    "辛里奇"
  ],
  "931": [
    "暮光",
    "绯闻",
    "澳大利亚",
    "美人图",
    "韩片"
  ],
  "932": [
    "a550",
    "索尼",
    "影像",
    "BIONZ",
    "Exmor"
  ],
  "933": [
    "邓肯",
    "马刺",
    "合同",
    "跳出",
    "退役"
  ],
  "934": [
    "姚明",
    "李慕豪",
    "周琦",
    "郑准",
    "国家队"
  ],
  "935": [
    "S90",
    "佳能",
    "S",
    "重出江湖",
    "沉寂"
  ],
  "936": [
    "The",
    "the",
    "斯巴达",
    "Love",
    "Meet"
  ],
  "937": [
    "电力公司",
    "怪兽",
    "飞屋",
    "游记",
    "筹备"
  ],
  "938": [
    "S930",
    "索尼",
    "2.4",
    "变焦镜头",
    "机身"
  ],
  "939": [
    "仓位",
    "基金",
    "经理",
    "ETF",
    "新高"
  ],
  "940": [
    "飙车",
    "狂野",
    "赛车",
    "Gameloft",
    "游戏"
  ],
  "941": [
    "基德",
    "裁判",
    "犯规",
    "失误",
    "湖人"
  ],
  "942": [
    "LUX4",
    "SUMMICRON",
    "限量版",
    "DC",
    "1.63"
  ],
  "943": [
    "企业",
    "山东电力",
    "保本",
    "金部",
    "焦扬"
  ],
  "944": [
    "大作",
    "育碧",
    "细胞分裂",
    "Yves",
    "信条"
  ],
  "945": [
    "J26",
    "富士",
    "FinePix",
    "夜景",
    "识别"
  ],
  "946": [
    "基金",
    "赎回",
    "季度末",
    "行业",
    "金融"
  ],
  "947": [
    "A500",
    "配备",
    "取景",
    "功能",
    "续航"
  ],
  "948": [
    "下跌",
    "跌幅",
    "ETF",
    "开盘",
    "0.44"
  ],
  "949": [
    "农银汇理",
    "交通银行",
    "农业银行",
    "基金",
    "优惠"
  ],
  "950": [
    "谢亚龙",
    "专案组",
    "介入",
    "口供",
    "调查"
  ],
  "951": [
    "SR87E",
    "索尼",
    "影像",
    "硬盘",
    "像素"
  ],
  "952": [
    "九州",
    "月度",
    "再起",
    "风云",
    "红颜"
  ],
  "953": [
    "V6000HDR",
    "艾诺",
    "飞毛腿",
    "支持",
    "格式"
  ],
  "954": [
    "常盘贵子",
    "漫画",
    "少年",
    "贤知",
    "世纪"
  ],
  "955": [
    "景宏",
    "基金",
    "净值",
    "分红",
    "金红利"
  ],
  "956": [
    "王秀琳",
    "咸猪",
    "拍剧",
    "尹天照",
    "香港"
  ],
  "957": [
    "老鹰",
    "魔术",
    "科林斯",
    "晋级",
    "霍华德"
  ],
  "958": [
    "波士顿",
    "TD",
    "花园",
    "韦德",
    "热火"
  ],
  "959": [
    "N20",
    "iriver",
    "耳机",
    "动铁",
    "IESE"
  ],
  "960": [
    "皮特",
    "克鲁尼",
    "电影节",
    "奥利维",
    "主席"
  ],
  "961": [
    "T900",
    "时尚",
    "索尼",
    "SONY",
    "DSC"
  ],
  "962": [
    "湖人",
    "进攻",
    "三角",
    "单打",
    "小牛"
  ],
  "963": [
    "皮埃尔",
    "皮昂",
    "名花",
    "浪漫",
    "影帝"
  ],
  "964": [
    "创业板",
    "主板",
    "市场",
    "基金",
    "企业"
  ],
  "965": [
    "Fox",
    "星空",
    "STAR",
    "印度",
    "电影"
  ],
  "966": [
    "数字",
    "历险记",
    "三维",
    "影院",
    "票房"
  ],
  "967": [
    "三国",
    "英雄",
    "印魂",
    "心目",
    "论坛"
  ],
  "968": [
    "QDII",
    "海富通",
    "分红",
    "基金",
    "中国"
  ],
  "969": [
    "MP3MP4",
    "T9HD",
    "蓝魔",
    "性价比",
    "产品"
  ],
  "970": [
    "工会",
    "罢工",
    "演员",
    "谈判",
    "电视"
  ],
  "971": [
    "封神",
    "礼包",
    "ol",
    "碎片",
    "小时"
  ],
  "972": [
    "VX510",
    "昂达",
    "流线",
    "济南",
    "靓丽"
  ],
  "973": [
    "基金",
    "分红",
    "排名",
    "QDII",
    "业绩"
  ],
  "974": [
    "冷却",
    "降低",
    "加成",
    "提高",
    "宝石"
  ],
  "975": [
    "工银",
    "风格",
    "晨星",
    "基金",
    "界定"
  ],
  "976": [
    "希特勒",
    "阿汤哥",
    "施陶芬",
    "克鲁斯",
    "汤姆"
  ],
  "977": [
    "PE",
    "自律",
    "协会",
    "行业",
    "监管"
  ],
  "978": [
    "T90",
    "索尼",
    "带票",
    "T77",
    "数码相机"
  ],
  "979": [
    "成立",
    "基金",
    "建仓",
    "净值",
    "涨幅"
  ],
  "980": [
    "希伯杜",
    "比赛",
    "阵容",
    "阿西",
    "磨合"
  ],
  "981": [
    "国联安",
    "精选",
    "李洪波",
    "经理",
    "基金"
  ],
  "982": [
    "票房",
    "万日元",
    "总动员",
    "亿日元",
    "东宝"
  ],
  "983": [
    "国海",
    "富兰克林",
    "全景网",
    "申购",
    "万元"
  ],
  "984": [
    "提名",
    "视觉效果",
    "工会",
    "钢铁",
    "The"
  ],
  "985": [
    "马刺",
    "邓肯",
    "帕克",
    "王朝",
    "看着"
  ],
  "986": [
    "Mark",
    "II",
    "D",
    "灰尘",
    "对焦"
  ],
  "987": [
    "九州",
    "奖励",
    "易小天",
    "再起",
    "风云"
  ],
  "988": [
    "小牛",
    "老板",
    "防守",
    "中心",
    "穿着"
  ],
  "989": [
    "贡献奖",
    "基金",
    "基金业",
    "易方达",
    "获金"
  ],
  "990": [
    "布莱恩",
    "火箭队",
    "沃格尔",
    "球队",
    "接班人"
  ],
  "991": [
    "申购",
    "限购",
    "基金",
    "曹磊",
    "单日"
  ],
  "992": [
    "雪球",
    "企业",
    "管理者",
    "投资",
    "保险"
  ],
  "993": [
    "湖人",
    "调查",
    "NBA",
    "险胜",
    "赢家"
  ],
  "994": [
    "冯小刚",
    "赵本山",
    "后脑勺",
    "刘双平",
    "刘能"
  ],
  "995": [
    "机构",
    "持股",
    "QFII",
    "增仓",
    "持仓"
  ],
  "996": [
    "俄罗斯",
    "阿列",
    "娇娃",
    "美女",
    "护宝"
  ],
  "997": [
    "罗伊",
    "罚球",
    "选秀",
    "第一场",
    "比赛"
  ],
  "998": [
    "霸王",
    "II",
    "新区",
    "玩家",
    "新春"
  ],
  "999": [
    "樟柯",
    "水城",
    "余力",
    "西河",
    "星汇"
  ],
  "1000": [
    "交银",
    "环球",
    "施罗德",
    "复活节",
    "申购"
  ]
}